Workbook

Sheet Apps
O1: 1000 | Q1: Weight | R1: 1000 | S1: 10 | T1: 10 | U1: 10 | V1: 5 | W1: 5 | X1: 5 | Y1: 3 | Z1: 1 | AA1: 1 | AB1: 1
A3: =J3&";"&K3&";"&B3&";"&C3&";"&D3&";"&E3&";"&F3&";"&G3&";"&H3&";"&I3 -> App;User Group;1;2;3;4;5;6;7;8 | B3: 1 | C3: 2 | D3: 3 | E3: 4 | F3: 5 | G3: 6 | H3: 7 | I3: 8 | J3: App | K3: User Group | L3: EUR (manual) | M3: EUR (analysis) | N3: EUR (cloc) | O3: EUR | P3: EUR/Unit | Q3: Units | R3: base | S3: mail | T3: product | U3: account | V3: website | W3: calendar,contact,hr,sale_management | X3: apps in use | Y3: apps | Z3: odoo | AA3: OCA | AB3: Other
A4: =J4&";"&K4&";"&B4&";"&C4&";"&D4&";"&E4&";"&F4&";"&G4&";"&H4&";"&I4 -> account;base.group_user;24;48;72;96;120;144;168;192 | B4: =$P4*MIN($Q4,B$3) -> 24 | C4: =$P4*MIN($Q4,C$3) -> 48 | D4: =$P4*MIN($Q4,D$3) -> 72 | E4: =$P4*MIN($Q4,E$3) -> 96 | F4: =$P4*MIN($Q4,F$3) -> 120 | G4: =$P4*MIN($Q4,G$3) -> 144 | H4: =$P4*MIN($Q4,H$3) -> 168 | I4: =$P4*MIN($Q4,I$3) -> 192 | J4: account | K4: base.group_user | M4: =INDEX('Pivot Analysis'!A:B,MATCH(J4,'Pivot Analysis'!B:B,0),1) -> 240 | N4: =INDEX(Cloc!E:F,MATCH(J4,Cloc!F:F,0),1) -> 2988.36 | O4: =IFERROR(IFERROR(IF(L4<>"",L4,M4),N4),$O$1) -> 240 | P4: =O4/Q4 -> 24 | Q4: =MAX(1,SUMPRODUCT($R$1:$AD$1,R4:AD4)) -> 10 | U4: 1 | X4: =IF(SUM(R4:W4)=0,VLOOKUP(J4,#REF!,1,0),"") | Y4: =IF(SUM(R4:X4)>0,"",VLOOKUP(J4,'Apps-from-odoo'!A:A,1,0))
A5: =J5&";"&K5&";"&B5&";"&C5&";"&D5&";"&E5&";"&F5&";"&G5&";"&H5&";"&I5 -> account_audit_trail;base.group_user;0;0;0;0;0;0;0;0 | B5: =$P5*MIN($Q5,B$3) -> 0 | C5: =$P5*MIN($Q5,C$3) -> 0 | D5: =$P5*MIN($Q5,D$3) -> 0 | E5: =$P5*MIN($Q5,E$3) -> 0 | F5: =$P5*MIN($Q5,F$3) -> 0 | G5: =$P5*MIN($Q5,G$3) -> 0 | H5: =$P5*MIN($Q5,H$3) -> 0 | I5: =$P5*MIN($Q5,I$3) -> 0 | J5: account_audit_trail | K5: base.group_user | M5: =INDEX('Pivot Analysis'!A:B,MATCH(J5,'Pivot Analysis'!B:B,0),1) -> 0 | N5: =INDEX(Cloc!E:F,MATCH(J5,Cloc!F:F,0),1) -> #N/A | O5: =IFERROR(IFERROR(IF(L5<>"",L5,M5),N5),$O$1) -> 0 | P5: =O5/Q5 -> 0 | Q5: =MAX(1,SUMPRODUCT($R$1:$AD$1,R5:AD5)) -> 1
A6: =J6&";"&K6&";"&B6&";"&C6&";"&D6&";"&E6&";"&F6&";"&G6&";"&H6&";"&I6 -> account_check_printing;base.group_user;7,5;7,5;7,5;7,5;7,5;7,5;7,5;7,5 | B6: =$P6*MIN($Q6,B$3) -> 7.5 | C6: =$P6*MIN($Q6,C$3) -> 7.5 | D6: =$P6*MIN($Q6,D$3) -> 7.5 | E6: =$P6*MIN($Q6,E$3) -> 7.5 | F6: =$P6*MIN($Q6,F$3) -> 7.5 | G6: =$P6*MIN($Q6,G$3) -> 7.5 | H6: =$P6*MIN($Q6,H$3) -> 7.5 | I6: =$P6*MIN($Q6,I$3) -> 7.5 | J6: account_check_printing | K6: base.group_user | M6: =INDEX('Pivot Analysis'!A:B,MATCH(J6,'Pivot Analysis'!B:B,0),1) -> 7.5 | N6: =INDEX(Cloc!E:F,MATCH(J6,Cloc!F:F,0),1) -> #N/A | O6: =IFERROR(IFERROR(IF(L6<>"",L6,M6),N6),$O$1) -> 7.5 | P6: =O6/Q6 -> 7.5 | Q6: =MAX(1,SUMPRODUCT($R$1:$AD$1,R6:AD6)) -> 1
A7: =J7&";"&K7&";"&B7&";"&C7&";"&D7&";"&E7&";"&F7&";"&G7&";"&H7&";"&I7 -> account_debit_note;base.group_user;34,5;34,5;34,5;34,5;34,5;34,5;34,5;34,5 | B7: =$P7*MIN($Q7,B$3) -> 34.5 | C7: =$P7*MIN($Q7,C$3) -> 34.5 | D7: =$P7*MIN($Q7,D$3) -> 34.5 | E7: =$P7*MIN($Q7,E$3) -> 34.5 | F7: =$P7*MIN($Q7,F$3) -> 34.5 | G7: =$P7*MIN($Q7,G$3) -> 34.5 | H7: =$P7*MIN($Q7,H$3) -> 34.5 | I7: =$P7*MIN($Q7,I$3) -> 34.5 | J7: account_debit_note | K7: base.group_user | M7: =INDEX('Pivot Analysis'!A:B,MATCH(J7,'Pivot Analysis'!B:B,0),1) -> 34.5 | N7: =INDEX(Cloc!E:F,MATCH(J7,Cloc!F:F,0),1) -> #N/A | O7: =IFERROR(IFERROR(IF(L7<>"",L7,M7),N7),$O$1) -> 34.5 | P7: =O7/Q7 -> 34.5 | Q7: =MAX(1,SUMPRODUCT($R$1:$AD$1,R7:AD7)) -> 1
A8: =J8&";"&K8&";"&B8&";"&C8&";"&D8&";"&E8&";"&F8&";"&G8&";"&H8&";"&I8 -> account_edi;base.group_user;0;0;0;0;0;0;0;0 | B8: =$P8*MIN($Q8,B$3) -> 0 | C8: =$P8*MIN($Q8,C$3) -> 0 | D8: =$P8*MIN($Q8,D$3) -> 0 | E8: =$P8*MIN($Q8,E$3) -> 0 | F8: =$P8*MIN($Q8,F$3) -> 0 | G8: =$P8*MIN($Q8,G$3) -> 0 | H8: =$P8*MIN($Q8,H$3) -> 0 | I8: =$P8*MIN($Q8,I$3) -> 0 | J8: account_edi | K8: base.group_user | M8: =INDEX('Pivot Analysis'!A:B,MATCH(J8,'Pivot Analysis'!B:B,0),1) -> 0 | N8: =INDEX(Cloc!E:F,MATCH(J8,Cloc!F:F,0),1) -> #N/A | O8: =IFERROR(IFERROR(IF(L8<>"",L8,M8),N8),$O$1) -> 0 | P8: =O8/Q8 -> 0 | Q8: =MAX(1,SUMPRODUCT($R$1:$AD$1,R8:AD8)) -> 1
A9: =J9&";"&K9&";"&B9&";"&C9&";"&D9&";"&E9&";"&F9&";"&G9&";"&H9&";"&I9 -> account_edi_proxy_client;base.group_user;81;81;81;81;81;81;81;81 | B9: =$P9*MIN($Q9,B$3) -> 81 | C9: =$P9*MIN($Q9,C$3) -> 81 | D9: =$P9*MIN($Q9,D$3) -> 81 | E9: =$P9*MIN($Q9,E$3) -> 81 | F9: =$P9*MIN($Q9,F$3) -> 81 | G9: =$P9*MIN($Q9,G$3) -> 81 | H9: =$P9*MIN($Q9,H$3) -> 81 | I9: =$P9*MIN($Q9,I$3) -> 81 | J9: account_edi_proxy_client | K9: base.group_user | M9: =INDEX('Pivot Analysis'!A:B,MATCH(J9,'Pivot Analysis'!B:B,0),1) -> 81 | N9: =INDEX(Cloc!E:F,MATCH(J9,Cloc!F:F,0),1) -> #N/A | O9: =IFERROR(IFERROR(IF(L9<>"",L9,M9),N9),$O$1) -> 81 | P9: =O9/Q9 -> 81 | Q9: =MAX(1,SUMPRODUCT($R$1:$AD$1,R9:AD9)) -> 1
A10: =J10&";"&K10&";"&B10&";"&C10&";"&D10&";"&E10&";"&F10&";"&G10&";"&H10&";"&I10 -> account_edi_ubl_cii;base.group_user;1,23;2,46;3,69;4,92;6,15;7,38;8,61;9,84 | B10: =$P10*MIN($Q10,B$3) -> 1.23 | C10: =$P10*MIN($Q10,C$3) -> 2.46 | D10: =$P10*MIN($Q10,D$3) -> 3.69 | E10: =$P10*MIN($Q10,E$3) -> 4.92 | F10: =$P10*MIN($Q10,F$3) -> 6.15 | G10: =$P10*MIN($Q10,G$3) -> 7.38 | H10: =$P10*MIN($Q10,H$3) -> 8.61 | I10: =$P10*MIN($Q10,I$3) -> 9.84 | J10: account_edi_ubl_cii | K10: base.group_user | M10: =INDEX('Pivot Analysis'!A:B,MATCH(J10,'Pivot Analysis'!B:B,0),1) -> 12.3 | N10: =INDEX(Cloc!E:F,MATCH(J10,Cloc!F:F,0),1) -> 284.1 | O10: =IFERROR(IFERROR(IF(L10<>"",L10,M10),N10),$O$1) -> 12.3 | P10: =O10/Q10 -> 1.23 | Q10: =MAX(1,SUMPRODUCT($R$1:$AD$1,R10:AD10)) -> 10 | U10: 1 | X10: =IF(SUM(R10:W10)=0,VLOOKUP(J10,#REF!,1,0),"") | Y10: =IF(SUM(R10:X10)>0,"",VLOOKUP(J10,'Apps-from-odoo'!A:A,1,0))
A11: =J11&";"&K11&";"&B11&";"&C11&";"&D11&";"&E11&";"&F11&";"&G11&";"&H11&";"&I11 -> account_edi_ubl_cii_tax_extension;base.group_user;0;0;0;0;0;0;0;0 | B11: =$P11*MIN($Q11,B$3) -> 0 | C11: =$P11*MIN($Q11,C$3) -> 0 | D11: =$P11*MIN($Q11,D$3) -> 0 | E11: =$P11*MIN($Q11,E$3) -> 0 | F11: =$P11*MIN($Q11,F$3) -> 0 | G11: =$P11*MIN($Q11,G$3) -> 0 | H11: =$P11*MIN($Q11,H$3) -> 0 | I11: =$P11*MIN($Q11,I$3) -> 0 | J11: account_edi_ubl_cii_tax_extension | K11: base.group_user | M11: =INDEX('Pivot Analysis'!A:B,MATCH(J11,'Pivot Analysis'!B:B,0),1) -> 0 | N11: =INDEX(Cloc!E:F,MATCH(J11,Cloc!F:F,0),1) -> #N/A | O11: =IFERROR(IFERROR(IF(L11<>"",L11,M11),N11),$O$1) -> 0 | P11: =O11/Q11 -> 0 | Q11: =MAX(1,SUMPRODUCT($R$1:$AD$1,R11:AD11)) -> 1
A12: =J12&";"&K12&";"&B12&";"&C12&";"&D12&";"&E12&";"&F12&";"&G12&";"&H12&";"&I12 -> account_fleet;base.group_user;1,5;3;4,5;6;7,5;7,5;7,5;7,5 | B12: =$P12*MIN($Q12,B$3) -> 1.5 | C12: =$P12*MIN($Q12,C$3) -> 3 | D12: =$P12*MIN($Q12,D$3) -> 4.5 | E12: =$P12*MIN($Q12,E$3) -> 6 | F12: =$P12*MIN($Q12,F$3) -> 7.5 | G12: =$P12*MIN($Q12,G$3) -> 7.5 | H12: =$P12*MIN($Q12,H$3) -> 7.5 | I12: =$P12*MIN($Q12,I$3) -> 7.5 | J12: account_fleet | K12: base.group_user | M12: =INDEX('Pivot Analysis'!A:B,MATCH(J12,'Pivot Analysis'!B:B,0),1) -> 7.5 | N12: =INDEX(Cloc!E:F,MATCH(J12,Cloc!F:F,0),1) -> 17.28 | O12: =IFERROR(IFERROR(IF(L12<>"",L12,M12),N12),$O$1) -> 7.5 | P12: =O12/Q12 -> 1.5 | Q12: =MAX(1,SUMPRODUCT($R$1:$AD$1,R12:AD12)) -> 5 | X12: 1 | Y12: =IF(SUM(R12:X12)>0,"",VLOOKUP(J12,'Apps-from-odoo'!A:A,1,0))
A13: =J13&";"&K13&";"&B13&";"&C13&";"&D13&";"&E13&";"&F13&";"&G13&";"&H13&";"&I13 -> account_lock;base.group_user;30;30;30;30;30;30;30;30 | B13: =$P13*MIN($Q13,B$3) -> 30 | C13: =$P13*MIN($Q13,C$3) -> 30 | D13: =$P13*MIN($Q13,D$3) -> 30 | E13: =$P13*MIN($Q13,E$3) -> 30 | F13: =$P13*MIN($Q13,F$3) -> 30 | G13: =$P13*MIN($Q13,G$3) -> 30 | H13: =$P13*MIN($Q13,H$3) -> 30 | I13: =$P13*MIN($Q13,I$3) -> 30 | J13: account_lock | K13: base.group_user | M13: =INDEX('Pivot Analysis'!A:B,MATCH(J13,'Pivot Analysis'!B:B,0),1) -> 30 | N13: =INDEX(Cloc!E:F,MATCH(J13,Cloc!F:F,0),1) -> #N/A | O13: =IFERROR(IFERROR(IF(L13<>"",L13,M13),N13),$O$1) -> 30 | P13: =O13/Q13 -> 30 | Q13: =MAX(1,SUMPRODUCT($R$1:$AD$1,R13:AD13)) -> 1
A14: =J14&";"&K14&";"&B14&";"&C14&";"&D14&";"&E14&";"&F14&";"&G14&";"&H14&";"&I14 -> account_payment;base.group_user;0,33;0,66;0,99;1,32;1,65;1,98;2,31;2,64 | B14: =$P14*MIN($Q14,B$3) -> 0.33 | C14: =$P14*MIN($Q14,C$3) -> 0.66 | D14: =$P14*MIN($Q14,D$3) -> 0.99 | E14: =$P14*MIN($Q14,E$3) -> 1.32 | F14: =$P14*MIN($Q14,F$3) -> 1.65 | G14: =$P14*MIN($Q14,G$3) -> 1.98 | H14: =$P14*MIN($Q14,H$3) -> 2.31 | I14: =$P14*MIN($Q14,I$3) -> 2.64 | J14: account_payment | K14: base.group_user | M14: =INDEX('Pivot Analysis'!A:B,MATCH(J14,'Pivot Analysis'!B:B,0),1) -> 3.3 | N14: =INDEX(Cloc!E:F,MATCH(J14,Cloc!F:F,0),1) -> 140.94 | O14: =IFERROR(IFERROR(IF(L14<>"",L14,M14),N14),$O$1) -> 3.3 | P14: =O14/Q14 -> 0.33 | Q14: =MAX(1,SUMPRODUCT($R$1:$AD$1,R14:AD14)) -> 10 | U14: 1 | X14: =IF(SUM(R14:W14)=0,VLOOKUP(J14,#REF!,1,0),"") | Y14: =IF(SUM(R14:X14)>0,"",VLOOKUP(J14,'Apps-from-odoo'!A:A,1,0))
A15: =J15&";"&K15&";"&B15&";"&C15&";"&D15&";"&E15&";"&F15&";"&G15&";"&H15&";"&I15 -> account_payment_invoice_online_payment_patch;base.group_user;0;0;0;0;0;0;0;0 | B15: =$P15*MIN($Q15,B$3) -> 0 | C15: =$P15*MIN($Q15,C$3) -> 0 | D15: =$P15*MIN($Q15,D$3) -> 0 | E15: =$P15*MIN($Q15,E$3) -> 0 | F15: =$P15*MIN($Q15,F$3) -> 0 | G15: =$P15*MIN($Q15,G$3) -> 0 | H15: =$P15*MIN($Q15,H$3) -> 0 | I15: =$P15*MIN($Q15,I$3) -> 0 | J15: account_payment_invoice_online_payment_patch | K15: base.group_user | M15: =INDEX('Pivot Analysis'!A:B,MATCH(J15,'Pivot Analysis'!B:B,0),1) -> 0 | N15: =INDEX(Cloc!E:F,MATCH(J15,Cloc!F:F,0),1) -> #N/A | O15: =IFERROR(IFERROR(IF(L15<>"",L15,M15),N15),$O$1) -> 0 | P15: =O15/Q15 -> 0 | Q15: =MAX(1,SUMPRODUCT($R$1:$AD$1,R15:AD15)) -> 1
A16: =J16&";"&K16&";"&B16&";"&C16&";"&D16&";"&E16&";"&F16&";"&G16&";"&H16&";"&I16 -> account_payment_term;base.group_user;0;0;0;0;0;0;0;0 | B16: =$P16*MIN($Q16,B$3) -> 0 | C16: =$P16*MIN($Q16,C$3) -> 0 | D16: =$P16*MIN($Q16,D$3) -> 0 | E16: =$P16*MIN($Q16,E$3) -> 0 | F16: =$P16*MIN($Q16,F$3) -> 0 | G16: =$P16*MIN($Q16,G$3) -> 0 | H16: =$P16*MIN($Q16,H$3) -> 0 | I16: =$P16*MIN($Q16,I$3) -> 0 | J16: account_payment_term | K16: base.group_user | M16: =INDEX('Pivot Analysis'!A:B,MATCH(J16,'Pivot Analysis'!B:B,0),1) -> 0 | N16: =INDEX(Cloc!E:F,MATCH(J16,Cloc!F:F,0),1) -> #N/A | O16: =IFERROR(IFERROR(IF(L16<>"",L16,M16),N16),$O$1) -> 0 | P16: =O16/Q16 -> 0 | Q16: =MAX(1,SUMPRODUCT($R$1:$AD$1,R16:AD16)) -> 1
A17: =J17&";"&K17&";"&B17&";"&C17&";"&D17&";"&E17&";"&F17&";"&G17&";"&H17&";"&I17 -> account_peppol;base.group_user;258;258;258;258;258;258;258;258 | B17: =$P17*MIN($Q17,B$3) -> 258 | C17: =$P17*MIN($Q17,C$3) -> 258 | D17: =$P17*MIN($Q17,D$3) -> 258 | E17: =$P17*MIN($Q17,E$3) -> 258 | F17: =$P17*MIN($Q17,F$3) -> 258 | G17: =$P17*MIN($Q17,G$3) -> 258 | H17: =$P17*MIN($Q17,H$3) -> 258 | I17: =$P17*MIN($Q17,I$3) -> 258 | J17: account_peppol | K17: base.group_user | M17: =INDEX('Pivot Analysis'!A:B,MATCH(J17,'Pivot Analysis'!B:B,0),1) -> 258 | N17: =INDEX(Cloc!E:F,MATCH(J17,Cloc!F:F,0),1) -> #N/A | O17: =IFERROR(IFERROR(IF(L17<>"",L17,M17),N17),$O$1) -> 258 | P17: =O17/Q17 -> 258 | Q17: =MAX(1,SUMPRODUCT($R$1:$AD$1,R17:AD17)) -> 1
A18: =J18&";"&K18&";"&B18&";"&C18&";"&D18&";"&E18&";"&F18&";"&G18&";"&H18&";"&I18 -> account_qr_code_emv;base.group_user;45;45;45;45;45;45;45;45 | B18: =$P18*MIN($Q18,B$3) -> 45 | C18: =$P18*MIN($Q18,C$3) -> 45 | D18: =$P18*MIN($Q18,D$3) -> 45 | E18: =$P18*MIN($Q18,E$3) -> 45 | F18: =$P18*MIN($Q18,F$3) -> 45 | G18: =$P18*MIN($Q18,G$3) -> 45 | H18: =$P18*MIN($Q18,H$3) -> 45 | I18: =$P18*MIN($Q18,I$3) -> 45 | J18: account_qr_code_emv | K18: base.group_user | M18: =INDEX('Pivot Analysis'!A:B,MATCH(J18,'Pivot Analysis'!B:B,0),1) -> 45 | N18: =INDEX(Cloc!E:F,MATCH(J18,Cloc!F:F,0),1) -> #N/A | O18: =IFERROR(IFERROR(IF(L18<>"",L18,M18),N18),$O$1) -> 45 | P18: =O18/Q18 -> 45 | Q18: =MAX(1,SUMPRODUCT($R$1:$AD$1,R18:AD18)) -> 1
A19: =J19&";"&K19&";"&B19&";"&C19&";"&D19&";"&E19&";"&F19&";"&G19&";"&H19&";"&I19 -> account_qr_code_sepa;base.group_user;3;3;3;3;3;3;3;3 | B19: =$P19*MIN($Q19,B$3) -> 3 | C19: =$P19*MIN($Q19,C$3) -> 3 | D19: =$P19*MIN($Q19,D$3) -> 3 | E19: =$P19*MIN($Q19,E$3) -> 3 | F19: =$P19*MIN($Q19,F$3) -> 3 | G19: =$P19*MIN($Q19,G$3) -> 3 | H19: =$P19*MIN($Q19,H$3) -> 3 | I19: =$P19*MIN($Q19,I$3) -> 3 | J19: account_qr_code_sepa | K19: base.group_user | M19: =INDEX('Pivot Analysis'!A:B,MATCH(J19,'Pivot Analysis'!B:B,0),1) -> 3 | N19: =INDEX(Cloc!E:F,MATCH(J19,Cloc!F:F,0),1) -> #N/A | O19: =IFERROR(IFERROR(IF(L19<>"",L19,M19),N19),$O$1) -> 3 | P19: =O19/Q19 -> 3 | Q19: =MAX(1,SUMPRODUCT($R$1:$AD$1,R19:AD19)) -> 1
A20: =J20&";"&K20&";"&B20&";"&C20&";"&D20&";"&E20&";"&F20&";"&G20&";"&H20&";"&I20 -> account_sequence;base.group_user;0;0;0;0;0;0;0;0 | B20: =$P20*MIN($Q20,B$3) -> 0 | C20: =$P20*MIN($Q20,C$3) -> 0 | D20: =$P20*MIN($Q20,D$3) -> 0 | E20: =$P20*MIN($Q20,E$3) -> 0 | F20: =$P20*MIN($Q20,F$3) -> 0 | G20: =$P20*MIN($Q20,G$3) -> 0 | H20: =$P20*MIN($Q20,H$3) -> 0 | I20: =$P20*MIN($Q20,I$3) -> 0 | J20: account_sequence | K20: base.group_user | M20: =INDEX('Pivot Analysis'!A:B,MATCH(J20,'Pivot Analysis'!B:B,0),1) -> 0 | N20: =INDEX(Cloc!E:F,MATCH(J20,Cloc!F:F,0),1) -> #N/A | O20: =IFERROR(IFERROR(IF(L20<>"",L20,M20),N20),$O$1) -> 0 | P20: =O20/Q20 -> 0 | Q20: =MAX(1,SUMPRODUCT($R$1:$AD$1,R20:AD20)) -> 1
A21: =J21&";"&K21&";"&B21&";"&C21&";"&D21&";"&E21&";"&F21&";"&G21&";"&H21&";"&I21 -> account_tax_python;base.group_user;82,5;82,5;82,5;82,5;82,5;82,5;82,5;82,5 | B21: =$P21*MIN($Q21,B$3) -> 82.5 | C21: =$P21*MIN($Q21,C$3) -> 82.5 | D21: =$P21*MIN($Q21,D$3) -> 82.5 | E21: =$P21*MIN($Q21,E$3) -> 82.5 | F21: =$P21*MIN($Q21,F$3) -> 82.5 | G21: =$P21*MIN($Q21,G$3) -> 82.5 | H21: =$P21*MIN($Q21,H$3) -> 82.5 | I21: =$P21*MIN($Q21,I$3) -> 82.5 | J21: account_tax_python | K21: base.group_user | M21: =INDEX('Pivot Analysis'!A:B,MATCH(J21,'Pivot Analysis'!B:B,0),1) -> 82.5 | N21: =INDEX(Cloc!E:F,MATCH(J21,Cloc!F:F,0),1) -> #N/A | O21: =IFERROR(IFERROR(IF(L21<>"",L21,M21),N21),$O$1) -> 82.5 | P21: =O21/Q21 -> 82.5 | Q21: =MAX(1,SUMPRODUCT($R$1:$AD$1,R21:AD21)) -> 1
A22: =J22&";"&K22&";"&B22&";"&C22&";"&D22&";"&E22&";"&F22&";"&G22&";"&H22&";"&I22 -> account_test;base.group_user;33;33;33;33;33;33;33;33 | B22: =$P22*MIN($Q22,B$3) -> 33 | C22: =$P22*MIN($Q22,C$3) -> 33 | D22: =$P22*MIN($Q22,D$3) -> 33 | E22: =$P22*MIN($Q22,E$3) -> 33 | F22: =$P22*MIN($Q22,F$3) -> 33 | G22: =$P22*MIN($Q22,G$3) -> 33 | H22: =$P22*MIN($Q22,H$3) -> 33 | I22: =$P22*MIN($Q22,I$3) -> 33 | J22: account_test | K22: base.group_user | M22: =INDEX('Pivot Analysis'!A:B,MATCH(J22,'Pivot Analysis'!B:B,0),1) -> 33 | N22: =INDEX(Cloc!E:F,MATCH(J22,Cloc!F:F,0),1) -> #N/A | O22: =IFERROR(IFERROR(IF(L22<>"",L22,M22),N22),$O$1) -> 33 | P22: =O22/Q22 -> 33 | Q22: =MAX(1,SUMPRODUCT($R$1:$AD$1,R22:AD22)) -> 1
A23: =J23&";"&K23&";"&B23&";"&C23&";"&D23&";"&E23&";"&F23&";"&G23&";"&H23&";"&I23 -> account_update_tax_tags;base.group_user;0;0;0;0;0;0;0;0 | B23: =$P23*MIN($Q23,B$3) -> 0 | C23: =$P23*MIN($Q23,C$3) -> 0 | D23: =$P23*MIN($Q23,D$3) -> 0 | E23: =$P23*MIN($Q23,E$3) -> 0 | F23: =$P23*MIN($Q23,F$3) -> 0 | G23: =$P23*MIN($Q23,G$3) -> 0 | H23: =$P23*MIN($Q23,H$3) -> 0 | I23: =$P23*MIN($Q23,I$3) -> 0 | J23: account_update_tax_tags | K23: base.group_user | M23: =INDEX('Pivot Analysis'!A:B,MATCH(J23,'Pivot Analysis'!B:B,0),1) -> 0 | N23: =INDEX(Cloc!E:F,MATCH(J23,Cloc!F:F,0),1) -> #N/A | O23: =IFERROR(IFERROR(IF(L23<>"",L23,M23),N23),$O$1) -> 0 | P23: =O23/Q23 -> 0 | Q23: =MAX(1,SUMPRODUCT($R$1:$AD$1,R23:AD23)) -> 1
A24: =J24&";"&K24&";"&B24&";"&C24&";"&D24&";"&E24&";"&F24&";"&G24&";"&H24&";"&I24 -> accountant;base.group_user;1000;1000;1000;1000;1000;1000;1000;1000 | B24: =$P24*MIN($Q24,B$3) -> 1000 | C24: =$P24*MIN($Q24,C$3) -> 1000 | D24: =$P24*MIN($Q24,D$3) -> 1000 | E24: =$P24*MIN($Q24,E$3) -> 1000 | F24: =$P24*MIN($Q24,F$3) -> 1000 | G24: =$P24*MIN($Q24,G$3) -> 1000 | H24: =$P24*MIN($Q24,H$3) -> 1000 | I24: =$P24*MIN($Q24,I$3) -> 1000 | J24: accountant | K24: base.group_user | M24: =INDEX('Pivot Analysis'!A:B,MATCH(J24,'Pivot Analysis'!B:B,0),1) -> #N/A | N24: =INDEX(Cloc!E:F,MATCH(J24,Cloc!F:F,0),1) -> #N/A | O24: =IFERROR(IFERROR(IF(L24<>"",L24,M24),N24),$O$1) -> 1000 | P24: =O24/Q24 -> 1000 | Q24: =MAX(1,SUMPRODUCT($R$1:$AD$1,R24:AD24)) -> 1 | Z24: 1
A25: =J25&";"&K25&";"&B25&";"&C25&";"&D25&";"&E25&";"&F25&";"&G25&";"&H25&";"&I25 -> analytic;base.group_user;0;0;0;0;0;0;0;0 | B25: =$P25*MIN($Q25,B$3) -> 0 | C25: =$P25*MIN($Q25,C$3) -> 0 | D25: =$P25*MIN($Q25,D$3) -> 0 | E25: =$P25*MIN($Q25,E$3) -> 0 | F25: =$P25*MIN($Q25,F$3) -> 0 | G25: =$P25*MIN($Q25,G$3) -> 0 | H25: =$P25*MIN($Q25,H$3) -> 0 | I25: =$P25*MIN($Q25,I$3) -> 0 | J25: analytic | K25: base.group_user | M25: =INDEX('Pivot Analysis'!A:B,MATCH(J25,'Pivot Analysis'!B:B,0),1) -> 0 | N25: =INDEX(Cloc!E:F,MATCH(J25,Cloc!F:F,0),1) -> 150 | O25: =IFERROR(IFERROR(IF(L25<>"",L25,M25),N25),$O$1) -> 0 | P25: =O25/Q25 -> 0 | Q25: =MAX(1,SUMPRODUCT($R$1:$AD$1,R25:AD25)) -> 10 | U25: 1 | X25: =IF(SUM(R25:W25)=0,VLOOKUP(J25,#REF!,1,0),"") | Y25: =IF(SUM(R25:X25)>0,"",VLOOKUP(J25,'Apps-from-odoo'!A:A,1,0))
A26: =J26&";"&K26&";"&B26&";"&C26&";"&D26&";"&E26&";"&F26&";"&G26&";"&H26&";"&I26 -> association;base.group_user;0;0;0;0;0;0;0;0 | B26: =$P26*MIN($Q26,B$3) -> 0 | C26: =$P26*MIN($Q26,C$3) -> 0 | D26: =$P26*MIN($Q26,D$3) -> 0 | E26: =$P26*MIN($Q26,E$3) -> 0 | F26: =$P26*MIN($Q26,F$3) -> 0 | G26: =$P26*MIN($Q26,G$3) -> 0 | H26: =$P26*MIN($Q26,H$3) -> 0 | I26: =$P26*MIN($Q26,I$3) -> 0 | J26: association | K26: base.group_user | M26: =INDEX('Pivot Analysis'!A:B,MATCH(J26,'Pivot Analysis'!B:B,0),1) -> 0 | N26: =INDEX(Cloc!E:F,MATCH(J26,Cloc!F:F,0),1) -> #N/A | O26: =IFERROR(IFERROR(IF(L26<>"",L26,M26),N26),$O$1) -> 0 | P26: =O26/Q26 -> 0 | Q26: =MAX(1,SUMPRODUCT($R$1:$AD$1,R26:AD26)) -> 1
A27: =J27&";"&K27&";"&B27&";"&C27&";"&D27&";"&E27&";"&F27&";"&G27&";"&H27&";"&I27 -> attachment_indexation;base.group_user;1;2;3;3;3;3;3;3 | B27: =$P27*MIN($Q27,B$3) -> 1 | C27: =$P27*MIN($Q27,C$3) -> 2 | D27: =$P27*MIN($Q27,D$3) -> 3 | E27: =$P27*MIN($Q27,E$3) -> 3 | F27: =$P27*MIN($Q27,F$3) -> 3 | G27: =$P27*MIN($Q27,G$3) -> 3 | H27: =$P27*MIN($Q27,H$3) -> 3 | I27: =$P27*MIN($Q27,I$3) -> 3 | J27: attachment_indexation | K27: base.group_user | M27: =INDEX('Pivot Analysis'!A:B,MATCH(J27,'Pivot Analysis'!B:B,0),1) -> 3 | N27: =INDEX(Cloc!E:F,MATCH(J27,Cloc!F:F,0),1) -> 9.3 | O27: =IFERROR(IFERROR(IF(L27<>"",L27,M27),N27),$O$1) -> 3 | P27: =O27/Q27 -> 1 | Q27: =MAX(1,SUMPRODUCT($R$1:$AD$1,R27:AD27)) -> 3 | Y27: 1
A28: =J28&";"&K28&";"&B28&";"&C28&";"&D28&";"&E28&";"&F28&";"&G28&";"&H28&";"&I28 -> auth_ldap;base.group_user;0;0;0;0;0;0;0;0 | B28: =$P28*MIN($Q28,B$3) -> 0 | C28: =$P28*MIN($Q28,C$3) -> 0 | D28: =$P28*MIN($Q28,D$3) -> 0 | E28: =$P28*MIN($Q28,E$3) -> 0 | F28: =$P28*MIN($Q28,F$3) -> 0 | G28: =$P28*MIN($Q28,G$3) -> 0 | H28: =$P28*MIN($Q28,H$3) -> 0 | I28: =$P28*MIN($Q28,I$3) -> 0 | J28: auth_ldap | K28: base.group_user | M28: =INDEX('Pivot Analysis'!A:B,MATCH(J28,'Pivot Analysis'!B:B,0),1) -> 0 | N28: =INDEX(Cloc!E:F,MATCH(J28,Cloc!F:F,0),1) -> #N/A | O28: =IFERROR(IFERROR(IF(L28<>"",L28,M28),N28),$O$1) -> 0 | P28: =O28/Q28 -> 0 | Q28: =MAX(1,SUMPRODUCT($R$1:$AD$1,R28:AD28)) -> 1
A29: =J29&";"&K29&";"&B29&";"&C29&";"&D29&";"&E29&";"&F29&";"&G29&";"&H29&";"&I29 -> auth_oauth;base.group_user;0;0;0;0;0;0;0;0 | B29: =$P29*MIN($Q29,B$3) -> 0 | C29: =$P29*MIN($Q29,C$3) -> 0 | D29: =$P29*MIN($Q29,D$3) -> 0 | E29: =$P29*MIN($Q29,E$3) -> 0 | F29: =$P29*MIN($Q29,F$3) -> 0 | G29: =$P29*MIN($Q29,G$3) -> 0 | H29: =$P29*MIN($Q29,H$3) -> 0 | I29: =$P29*MIN($Q29,I$3) -> 0 | J29: auth_oauth | K29: base.group_user | M29: =INDEX('Pivot Analysis'!A:B,MATCH(J29,'Pivot Analysis'!B:B,0),1) -> 0 | N29: =INDEX(Cloc!E:F,MATCH(J29,Cloc!F:F,0),1) -> #N/A | O29: =IFERROR(IFERROR(IF(L29<>"",L29,M29),N29),$O$1) -> 0 | P29: =O29/Q29 -> 0 | Q29: =MAX(1,SUMPRODUCT($R$1:$AD$1,R29:AD29)) -> 1
A30: =J30&";"&K30&";"&B30&";"&C30&";"&D30&";"&E30&";"&F30&";"&G30&";"&H30&";"&I30 -> auth_passkey;base.group_user;1000;1000;1000;1000;1000;1000;1000;1000 | B30: =$P30*MIN($Q30,B$3) -> 1000 | C30: =$P30*MIN($Q30,C$3) -> 1000 | D30: =$P30*MIN($Q30,D$3) -> 1000 | E30: =$P30*MIN($Q30,E$3) -> 1000 | F30: =$P30*MIN($Q30,F$3) -> 1000 | G30: =$P30*MIN($Q30,G$3) -> 1000 | H30: =$P30*MIN($Q30,H$3) -> 1000 | I30: =$P30*MIN($Q30,I$3) -> 1000 | J30: auth_passkey | K30: base.group_user | M30: =INDEX('Pivot Analysis'!A:B,MATCH(J30,'Pivot Analysis'!B:B,0),1) -> #N/A | N30: =INDEX(Cloc!E:F,MATCH(J30,Cloc!F:F,0),1) -> #N/A | O30: =IFERROR(IFERROR(IF(L30<>"",L30,M30),N30),$O$1) -> 1000 | P30: =O30/Q30 -> 1000 | Q30: =MAX(1,SUMPRODUCT($R$1:$AD$1,R30:AD30)) -> 1 | Z30: 1
A31: =J31&";"&K31&";"&B31&";"&C31&";"&D31&";"&E31&";"&F31&";"&G31&";"&H31&";"&I31 -> auth_password_policy;base.group_user;3;3;3;3;3;3;3;3 | B31: =$P31*MIN($Q31,B$3) -> 3 | C31: =$P31*MIN($Q31,C$3) -> 3 | D31: =$P31*MIN($Q31,D$3) -> 3 | E31: =$P31*MIN($Q31,E$3) -> 3 | F31: =$P31*MIN($Q31,F$3) -> 3 | G31: =$P31*MIN($Q31,G$3) -> 3 | H31: =$P31*MIN($Q31,H$3) -> 3 | I31: =$P31*MIN($Q31,I$3) -> 3 | J31: auth_password_policy | K31: base.group_user | M31: =INDEX('Pivot Analysis'!A:B,MATCH(J31,'Pivot Analysis'!B:B,0),1) -> 3 | N31: =INDEX(Cloc!E:F,MATCH(J31,Cloc!F:F,0),1) -> #N/A | O31: =IFERROR(IFERROR(IF(L31<>"",L31,M31),N31),$O$1) -> 3 | P31: =O31/Q31 -> 3 | Q31: =MAX(1,SUMPRODUCT($R$1:$AD$1,R31:AD31)) -> 1
A32: =J32&";"&K32&";"&B32&";"&C32&";"&D32&";"&E32&";"&F32&";"&G32&";"&H32&";"&I32 -> auth_password_policy_portal;base.group_user;33;33;33;33;33;33;33;33 | B32: =$P32*MIN($Q32,B$3) -> 33 | C32: =$P32*MIN($Q32,C$3) -> 33 | D32: =$P32*MIN($Q32,D$3) -> 33 | E32: =$P32*MIN($Q32,E$3) -> 33 | F32: =$P32*MIN($Q32,F$3) -> 33 | G32: =$P32*MIN($Q32,G$3) -> 33 | H32: =$P32*MIN($Q32,H$3) -> 33 | I32: =$P32*MIN($Q32,I$3) -> 33 | J32: auth_password_policy_portal | K32: base.group_user | M32: =INDEX('Pivot Analysis'!A:B,MATCH(J32,'Pivot Analysis'!B:B,0),1) -> 33 | N32: =INDEX(Cloc!E:F,MATCH(J32,Cloc!F:F,0),1) -> #N/A | O32: =IFERROR(IFERROR(IF(L32<>"",L32,M32),N32),$O$1) -> 33 | P32: =O32/Q32 -> 33 | Q32: =MAX(1,SUMPRODUCT($R$1:$AD$1,R32:AD32)) -> 1
A33: =J33&";"&K33&";"&B33&";"&C33&";"&D33&";"&E33&";"&F33&";"&G33&";"&H33&";"&I33 -> auth_password_policy_signup;base.group_user;3;3;3;3;3;3;3;3 | B33: =$P33*MIN($Q33,B$3) -> 3 | C33: =$P33*MIN($Q33,C$3) -> 3 | D33: =$P33*MIN($Q33,D$3) -> 3 | E33: =$P33*MIN($Q33,E$3) -> 3 | F33: =$P33*MIN($Q33,F$3) -> 3 | G33: =$P33*MIN($Q33,G$3) -> 3 | H33: =$P33*MIN($Q33,H$3) -> 3 | I33: =$P33*MIN($Q33,I$3) -> 3 | J33: auth_password_policy_signup | K33: base.group_user | M33: =INDEX('Pivot Analysis'!A:B,MATCH(J33,'Pivot Analysis'!B:B,0),1) -> 3 | N33: =INDEX(Cloc!E:F,MATCH(J33,Cloc!F:F,0),1) -> #N/A | O33: =IFERROR(IFERROR(IF(L33<>"",L33,M33),N33),$O$1) -> 3 | P33: =O33/Q33 -> 3 | Q33: =MAX(1,SUMPRODUCT($R$1:$AD$1,R33:AD33)) -> 1
A34: =J34&";"&K34&";"&B34&";"&C34&";"&D34&";"&E34&";"&F34&";"&G34&";"&H34&";"&I34 -> auth_signup;base.group_user;0;0;0;0;0;0;0;0 | B34: =$P34*MIN($Q34,B$3) -> 0 | C34: =$P34*MIN($Q34,C$3) -> 0 | D34: =$P34*MIN($Q34,D$3) -> 0 | E34: =$P34*MIN($Q34,E$3) -> 0 | F34: =$P34*MIN($Q34,F$3) -> 0 | G34: =$P34*MIN($Q34,G$3) -> 0 | H34: =$P34*MIN($Q34,H$3) -> 0 | I34: =$P34*MIN($Q34,I$3) -> 0 | J34: auth_signup | K34: base.group_user | M34: =INDEX('Pivot Analysis'!A:B,MATCH(J34,'Pivot Analysis'!B:B,0),1) -> 0 | N34: =INDEX(Cloc!E:F,MATCH(J34,Cloc!F:F,0),1) -> 87.3 | O34: =IFERROR(IFERROR(IF(L34<>"",L34,M34),N34),$O$1) -> 0 | P34: =O34/Q34 -> 0 | Q34: =MAX(1,SUMPRODUCT($R$1:$AD$1,R34:AD34)) -> 10 | T34: 1 | X34: =IF(SUM(R34:W34)=0,VLOOKUP(J34,#REF!,1,0),"") | Y34: =IF(SUM(R34:X34)>0,"",VLOOKUP(J34,'Apps-from-odoo'!A:A,1,0))
A35: =J35&";"&K35&";"&B35&";"&C35&";"&D35&";"&E35&";"&F35&";"&G35&";"&H35&";"&I35 -> auth_totp;base.group_user;0;0;0;0;0;0;0;0 | B35: =$P35*MIN($Q35,B$3) -> 0 | C35: =$P35*MIN($Q35,C$3) -> 0 | D35: =$P35*MIN($Q35,D$3) -> 0 | E35: =$P35*MIN($Q35,E$3) -> 0 | F35: =$P35*MIN($Q35,F$3) -> 0 | G35: =$P35*MIN($Q35,G$3) -> 0 | H35: =$P35*MIN($Q35,H$3) -> 0 | I35: =$P35*MIN($Q35,I$3) -> 0 | J35: auth_totp | K35: base.group_user | M35: =INDEX('Pivot Analysis'!A:B,MATCH(J35,'Pivot Analysis'!B:B,0),1) -> 0 | N35: =INDEX(Cloc!E:F,MATCH(J35,Cloc!F:F,0),1) -> 43.86 | O35: =IFERROR(IFERROR(IF(L35<>"",L35,M35),N35),$O$1) -> 0 | P35: =O35/Q35 -> 0 | Q35: =MAX(1,SUMPRODUCT($R$1:$AD$1,R35:AD35)) -> 1000 | R35: 1 | X35: =IF(SUM(R35:W35)=0,VLOOKUP(J35,#REF!,1,0),"") | Y35: =IF(SUM(R35:X35)>0,"",VLOOKUP(J35,'Apps-from-odoo'!A:A,1,0))
A36: =J36&";"&K36&";"&B36&";"&C36&";"&D36&";"&E36&";"&F36&";"&G36&";"&H36&";"&I36 -> auth_totp_mail;base.group_user;0,3;0,6;0,9;1,2;1,5;1,8;2,1;2,4 | B36: =$P36*MIN($Q36,B$3) -> 0.3 | C36: =$P36*MIN($Q36,C$3) -> 0.6 | D36: =$P36*MIN($Q36,D$3) -> 0.9 | E36: =$P36*MIN($Q36,E$3) -> 1.2 | F36: =$P36*MIN($Q36,F$3) -> 1.5 | G36: =$P36*MIN($Q36,G$3) -> 1.8 | H36: =$P36*MIN($Q36,H$3) -> 2.1 | I36: =$P36*MIN($Q36,I$3) -> 2.4 | J36: auth_totp_mail | K36: base.group_user | M36: =INDEX('Pivot Analysis'!A:B,MATCH(J36,'Pivot Analysis'!B:B,0),1) -> 3 | N36: =INDEX(Cloc!E:F,MATCH(J36,Cloc!F:F,0),1) -> 15.06 | O36: =IFERROR(IFERROR(IF(L36<>"",L36,M36),N36),$O$1) -> 3 | P36: =O36/Q36 -> 0.3 | Q36: =MAX(1,SUMPRODUCT($R$1:$AD$1,R36:AD36)) -> 10 | T36: 1 | X36: =IF(SUM(R36:W36)=0,VLOOKUP(J36,#REF!,1,0),"") | Y36: =IF(SUM(R36:X36)>0,"",VLOOKUP(J36,'Apps-from-odoo'!A:A,1,0))
A37: =J37&";"&K37&";"&B37&";"&C37&";"&D37&";"&E37&";"&F37&";"&G37&";"&H37&";"&I37 -> auth_totp_mail_enforce;base.group_user;0;0;0;0;0;0;0;0 | B37: =$P37*MIN($Q37,B$3) -> 0 | C37: =$P37*MIN($Q37,C$3) -> 0 | D37: =$P37*MIN($Q37,D$3) -> 0 | E37: =$P37*MIN($Q37,E$3) -> 0 | F37: =$P37*MIN($Q37,F$3) -> 0 | G37: =$P37*MIN($Q37,G$3) -> 0 | H37: =$P37*MIN($Q37,H$3) -> 0 | I37: =$P37*MIN($Q37,I$3) -> 0 | J37: auth_totp_mail_enforce | K37: base.group_user | M37: =INDEX('Pivot Analysis'!A:B,MATCH(J37,'Pivot Analysis'!B:B,0),1) -> 0 | N37: =INDEX(Cloc!E:F,MATCH(J37,Cloc!F:F,0),1) -> #N/A | O37: =IFERROR(IFERROR(IF(L37<>"",L37,M37),N37),$O$1) -> 0 | P37: =O37/Q37 -> 0 | Q37: =MAX(1,SUMPRODUCT($R$1:$AD$1,R37:AD37)) -> 1
A38: =J38&";"&K38&";"&B38&";"&C38&";"&D38&";"&E38&";"&F38&";"&G38&";"&H38&";"&I38 -> auth_totp_portal;base.group_user;0,3;0,6;0,9;1,2;1,5;1,8;2,1;2,4 | B38: =$P38*MIN($Q38,B$3) -> 0.3 | C38: =$P38*MIN($Q38,C$3) -> 0.6 | D38: =$P38*MIN($Q38,D$3) -> 0.9 | E38: =$P38*MIN($Q38,E$3) -> 1.2 | F38: =$P38*MIN($Q38,F$3) -> 1.5 | G38: =$P38*MIN($Q38,G$3) -> 1.8 | H38: =$P38*MIN($Q38,H$3) -> 2.1 | I38: =$P38*MIN($Q38,I$3) -> 2.4 | J38: auth_totp_portal | K38: base.group_user | M38: =INDEX('Pivot Analysis'!A:B,MATCH(J38,'Pivot Analysis'!B:B,0),1) -> 3 | N38: =INDEX(Cloc!E:F,MATCH(J38,Cloc!F:F,0),1) -> 24.24 | O38: =IFERROR(IFERROR(IF(L38<>"",L38,M38),N38),$O$1) -> 3 | P38: =O38/Q38 -> 0.3 | Q38: =MAX(1,SUMPRODUCT($R$1:$AD$1,R38:AD38)) -> 10 | U38: 1 | X38: =IF(SUM(R38:W38)=0,VLOOKUP(J38,#REF!,1,0),"") | Y38: =IF(SUM(R38:X38)>0,"",VLOOKUP(J38,'Apps-from-odoo'!A:A,1,0))
A39: =J39&";"&K39&";"&B39&";"&C39&";"&D39&";"&E39&";"&F39&";"&G39&";"&H39&";"&I39 -> barcodes;base.group_user;0;0;0;0;0;0;0;0 | B39: =$P39*MIN($Q39,B$3) -> 0 | C39: =$P39*MIN($Q39,C$3) -> 0 | D39: =$P39*MIN($Q39,D$3) -> 0 | E39: =$P39*MIN($Q39,E$3) -> 0 | F39: =$P39*MIN($Q39,F$3) -> 0 | G39: =$P39*MIN($Q39,G$3) -> 0 | H39: =$P39*MIN($Q39,H$3) -> 0 | I39: =$P39*MIN($Q39,I$3) -> 0 | J39: barcodes | K39: base.group_user | M39: =INDEX('Pivot Analysis'!A:B,MATCH(J39,'Pivot Analysis'!B:B,0),1) -> 0 | N39: =INDEX(Cloc!E:F,MATCH(J39,Cloc!F:F,0),1) -> 68.7 | O39: =IFERROR(IFERROR(IF(L39<>"",L39,M39),N39),$O$1) -> 0 | P39: =O39/Q39 -> 0 | Q39: =MAX(1,SUMPRODUCT($R$1:$AD$1,R39:AD39)) -> 5 | X39: 1 | Y39: =IF(SUM(R39:X39)>0,"",VLOOKUP(J39,'Apps-from-odoo'!A:A,1,0))
A40: =J40&";"&K40&";"&B40&";"&C40&";"&D40&";"&E40&";"&F40&";"&G40&";"&H40&";"&I40 -> barcodes_gs1_nomenclature;base.group_user;0;0;0;0;0;0;0;0 | B40: =$P40*MIN($Q40,B$3) -> 0 | C40: =$P40*MIN($Q40,C$3) -> 0 | D40: =$P40*MIN($Q40,D$3) -> 0 | E40: =$P40*MIN($Q40,E$3) -> 0 | F40: =$P40*MIN($Q40,F$3) -> 0 | G40: =$P40*MIN($Q40,G$3) -> 0 | H40: =$P40*MIN($Q40,H$3) -> 0 | I40: =$P40*MIN($Q40,I$3) -> 0 | J40: barcodes_gs1_nomenclature | K40: base.group_user | M40: =INDEX('Pivot Analysis'!A:B,MATCH(J40,'Pivot Analysis'!B:B,0),1) -> 0 | N40: =INDEX(Cloc!E:F,MATCH(J40,Cloc!F:F,0),1) -> 67.38 | O40: =IFERROR(IFERROR(IF(L40<>"",L40,M40),N40),$O$1) -> 0 | P40: =O40/Q40 -> 0 | Q40: =MAX(1,SUMPRODUCT($R$1:$AD$1,R40:AD40)) -> 5 | X40: 1 | Y40: =IF(SUM(R40:X40)>0,"",VLOOKUP(J40,'Apps-from-odoo'!A:A,1,0))
A41: =J41&";"&K41&";"&B41&";"&C41&";"&D41&";"&E41&";"&F41&";"&G41&";"&H41&";"&I41 -> base;base.group_user;0;0;0;0;0;0;0;0 | B41: =$P41*MIN($Q41,B$3) -> 0 | C41: =$P41*MIN($Q41,C$3) -> 0 | D41: =$P41*MIN($Q41,D$3) -> 0 | E41: =$P41*MIN($Q41,E$3) -> 0 | F41: =$P41*MIN($Q41,F$3) -> 0 | G41: =$P41*MIN($Q41,G$3) -> 0 | H41: =$P41*MIN($Q41,H$3) -> 0 | I41: =$P41*MIN($Q41,I$3) -> 0 | J41: base | K41: base.group_user | M41: =INDEX('Pivot Analysis'!A:B,MATCH(J41,'Pivot Analysis'!B:B,0),1) -> 0 | N41: =INDEX(Cloc!E:F,MATCH(J41,Cloc!F:F,0),1) -> 2431.98 | O41: =IFERROR(IFERROR(IF(L41<>"",L41,M41),N41),$O$1) -> 0 | P41: =O41/Q41 -> 0 | Q41: =MAX(1,SUMPRODUCT($R$1:$AD$1,R41:AD41)) -> 1000 | R41: 1 | X41: =IF(SUM(R41:W41)=0,VLOOKUP(J41,#REF!,1,0),"") | Y41: =IF(SUM(R41:X41)>0,"",VLOOKUP(J41,'Apps-from-odoo'!A:A,1,0))
A42: =J42&";"&K42&";"&B42&";"&C42&";"&D42&";"&E42&";"&F42&";"&G42&";"&H42&";"&I42 -> base_address_extended;base.group_user;0;0;0;0;0;0;0;0 | B42: =$P42*MIN($Q42,B$3) -> 0 | C42: =$P42*MIN($Q42,C$3) -> 0 | D42: =$P42*MIN($Q42,D$3) -> 0 | E42: =$P42*MIN($Q42,E$3) -> 0 | F42: =$P42*MIN($Q42,F$3) -> 0 | G42: =$P42*MIN($Q42,G$3) -> 0 | H42: =$P42*MIN($Q42,H$3) -> 0 | I42: =$P42*MIN($Q42,I$3) -> 0 | J42: base_address_extended | K42: base.group_user | M42: =INDEX('Pivot Analysis'!A:B,MATCH(J42,'Pivot Analysis'!B:B,0),1) -> 0 | N42: =INDEX(Cloc!E:F,MATCH(J42,Cloc!F:F,0),1) -> #N/A | O42: =IFERROR(IFERROR(IF(L42<>"",L42,M42),N42),$O$1) -> 0 | P42: =O42/Q42 -> 0 | Q42: =MAX(1,SUMPRODUCT($R$1:$AD$1,R42:AD42)) -> 1
A43: =J43&";"&K43&";"&B43&";"&C43&";"&D43&";"&E43&";"&F43&";"&G43&";"&H43&";"&I43 -> base_app;base.group_user;0;0;0;0;0;0;0;0 | B43: =$P43*MIN($Q43,B$3) -> 0 | C43: =$P43*MIN($Q43,C$3) -> 0 | D43: =$P43*MIN($Q43,D$3) -> 0 | E43: =$P43*MIN($Q43,E$3) -> 0 | F43: =$P43*MIN($Q43,F$3) -> 0 | G43: =$P43*MIN($Q43,G$3) -> 0 | H43: =$P43*MIN($Q43,H$3) -> 0 | I43: =$P43*MIN($Q43,I$3) -> 0 | J43: base_app | K43: base.group_user | L43: 0 | M43: =INDEX('Pivot Analysis'!A:B,MATCH(J43,'Pivot Analysis'!B:B,0),1) -> #N/A | N43: =INDEX(Cloc!E:F,MATCH(J43,Cloc!F:F,0),1) -> 8.88 | O43: =IFERROR(IFERROR(IF(L43<>"",L43,M43),N43),$O$1) -> 0 | P43: =O43/Q43 -> 0 | Q43: =MAX(1,SUMPRODUCT($R$1:$AD$1,R43:AD43)) -> 1 | AB43: 1
A44: =J44&";"&K44&";"&B44&";"&C44&";"&D44&";"&E44&";"&F44&";"&G44&";"&H44&";"&I44 -> base_automation;base.group_user;288;288;288;288;288;288;288;288 | B44: =$P44*MIN($Q44,B$3) -> 288 | C44: =$P44*MIN($Q44,C$3) -> 288 | D44: =$P44*MIN($Q44,D$3) -> 288 | E44: =$P44*MIN($Q44,E$3) -> 288 | F44: =$P44*MIN($Q44,F$3) -> 288 | G44: =$P44*MIN($Q44,G$3) -> 288 | H44: =$P44*MIN($Q44,H$3) -> 288 | I44: =$P44*MIN($Q44,I$3) -> 288 | J44: base_automation | K44: base.group_user | M44: =INDEX('Pivot Analysis'!A:B,MATCH(J44,'Pivot Analysis'!B:B,0),1) -> 288 | N44: =INDEX(Cloc!E:F,MATCH(J44,Cloc!F:F,0),1) -> #N/A | O44: =IFERROR(IFERROR(IF(L44<>"",L44,M44),N44),$O$1) -> 288 | P44: =O44/Q44 -> 288 | Q44: =MAX(1,SUMPRODUCT($R$1:$AD$1,R44:AD44)) -> 1
A45: =J45&";"&K45&";"&B45&";"&C45&";"&D45&";"&E45&";"&F45&";"&G45&";"&H45&";"&I45 -> base_display_name;base.group_user;1000;1000;1000;1000;1000;1000;1000;1000 | B45: =$P45*MIN($Q45,B$3) -> 1000 | C45: =$P45*MIN($Q45,C$3) -> 1000 | D45: =$P45*MIN($Q45,D$3) -> 1000 | E45: =$P45*MIN($Q45,E$3) -> 1000 | F45: =$P45*MIN($Q45,F$3) -> 1000 | G45: =$P45*MIN($Q45,G$3) -> 1000 | H45: =$P45*MIN($Q45,H$3) -> 1000 | I45: =$P45*MIN($Q45,I$3) -> 1000 | J45: base_display_name | K45: base.group_user | M45: =INDEX('Pivot Analysis'!A:B,MATCH(J45,'Pivot Analysis'!B:B,0),1) -> #N/A | N45: =INDEX(Cloc!E:F,MATCH(J45,Cloc!F:F,0),1) -> #N/A | O45: =IFERROR(IFERROR(IF(L45<>"",L45,M45),N45),$O$1) -> 1000 | P45: =O45/Q45 -> 1000 | Q45: =MAX(1,SUMPRODUCT($R$1:$AD$1,R45:AD45)) -> 1 | AB45: 1
A46: =J46&";"&K46&";"&B46&";"&C46&";"&D46&";"&E46&";"&F46&";"&G46&";"&H46&";"&I46 -> base_geolocalize;base.group_user;0;0;0;0;0;0;0;0 | B46: =$P46*MIN($Q46,B$3) -> 0 | C46: =$P46*MIN($Q46,C$3) -> 0 | D46: =$P46*MIN($Q46,D$3) -> 0 | E46: =$P46*MIN($Q46,E$3) -> 0 | F46: =$P46*MIN($Q46,F$3) -> 0 | G46: =$P46*MIN($Q46,G$3) -> 0 | H46: =$P46*MIN($Q46,H$3) -> 0 | I46: =$P46*MIN($Q46,I$3) -> 0 | J46: base_geolocalize | K46: base.group_user | M46: =INDEX('Pivot Analysis'!A:B,MATCH(J46,'Pivot Analysis'!B:B,0),1) -> 0 | N46: =INDEX(Cloc!E:F,MATCH(J46,Cloc!F:F,0),1) -> #N/A | O46: =IFERROR(IFERROR(IF(L46<>"",L46,M46),N46),$O$1) -> 0 | P46: =O46/Q46 -> 0 | Q46: =MAX(1,SUMPRODUCT($R$1:$AD$1,R46:AD46)) -> 1
A47: =J47&";"&K47&";"&B47&";"&C47&";"&D47&";"&E47&";"&F47&";"&G47&";"&H47&";"&I47 -> base_iban;base.group_user;3;3;3;3;3;3;3;3 | B47: =$P47*MIN($Q47,B$3) -> 3 | C47: =$P47*MIN($Q47,C$3) -> 3 | D47: =$P47*MIN($Q47,D$3) -> 3 | E47: =$P47*MIN($Q47,E$3) -> 3 | F47: =$P47*MIN($Q47,F$3) -> 3 | G47: =$P47*MIN($Q47,G$3) -> 3 | H47: =$P47*MIN($Q47,H$3) -> 3 | I47: =$P47*MIN($Q47,I$3) -> 3 | J47: base_iban | K47: base.group_user | M47: =INDEX('Pivot Analysis'!A:B,MATCH(J47,'Pivot Analysis'!B:B,0),1) -> 3 | N47: =INDEX(Cloc!E:F,MATCH(J47,Cloc!F:F,0),1) -> #N/A | O47: =IFERROR(IFERROR(IF(L47<>"",L47,M47),N47),$O$1) -> 3 | P47: =O47/Q47 -> 3 | Q47: =MAX(1,SUMPRODUCT($R$1:$AD$1,R47:AD47)) -> 1
A48: =J48&";"&K48&";"&B48&";"&C48&";"&D48&";"&E48&";"&F48&";"&G48&";"&H48&";"&I48 -> base_import;base.group_user;0;0;0;0;0;0;0;0 | B48: =$P48*MIN($Q48,B$3) -> 0 | C48: =$P48*MIN($Q48,C$3) -> 0 | D48: =$P48*MIN($Q48,D$3) -> 0 | E48: =$P48*MIN($Q48,E$3) -> 0 | F48: =$P48*MIN($Q48,F$3) -> 0 | G48: =$P48*MIN($Q48,G$3) -> 0 | H48: =$P48*MIN($Q48,H$3) -> 0 | I48: =$P48*MIN($Q48,I$3) -> 0 | J48: base_import | K48: base.group_user | M48: =INDEX('Pivot Analysis'!A:B,MATCH(J48,'Pivot Analysis'!B:B,0),1) -> 0 | N48: =INDEX(Cloc!E:F,MATCH(J48,Cloc!F:F,0),1) -> 243.9 | O48: =IFERROR(IFERROR(IF(L48<>"",L48,M48),N48),$O$1) -> 0 | P48: =O48/Q48 -> 0 | Q48: =MAX(1,SUMPRODUCT($R$1:$AD$1,R48:AD48)) -> 1000 | R48: 1 | X48: =IF(SUM(R48:W48)=0,VLOOKUP(J48,#REF!,1,0),"") | Y48: =IF(SUM(R48:X48)>0,"",VLOOKUP(J48,'Apps-from-odoo'!A:A,1,0))
A49: =J49&";"&K49&";"&B49&";"&C49&";"&D49&";"&E49&";"&F49&";"&G49&";"&H49&";"&I49 -> base_import_module;base.group_user;0;0;0;0;0;0;0;0 | B49: =$P49*MIN($Q49,B$3) -> 0 | C49: =$P49*MIN($Q49,C$3) -> 0 | D49: =$P49*MIN($Q49,D$3) -> 0 | E49: =$P49*MIN($Q49,E$3) -> 0 | F49: =$P49*MIN($Q49,F$3) -> 0 | G49: =$P49*MIN($Q49,G$3) -> 0 | H49: =$P49*MIN($Q49,H$3) -> 0 | I49: =$P49*MIN($Q49,I$3) -> 0 | J49: base_import_module | K49: base.group_user | M49: =INDEX('Pivot Analysis'!A:B,MATCH(J49,'Pivot Analysis'!B:B,0),1) -> 0 | N49: =INDEX(Cloc!E:F,MATCH(J49,Cloc!F:F,0),1) -> 51.48 | O49: =IFERROR(IFERROR(IF(L49<>"",L49,M49),N49),$O$1) -> 0 | P49: =O49/Q49 -> 0 | Q49: =MAX(1,SUMPRODUCT($R$1:$AD$1,R49:AD49)) -> 1000 | R49: 1 | X49: =IF(SUM(R49:W49)=0,VLOOKUP(J49,#REF!,1,0),"") | Y49: =IF(SUM(R49:X49)>0,"",VLOOKUP(J49,'Apps-from-odoo'!A:A,1,0))
A50: =J50&";"&K50&";"&B50&";"&C50&";"&D50&";"&E50&";"&F50&";"&G50&";"&H50&";"&I50 -> base_install_request;base.group_user;0,3;0,6;0,9;1,2;1,5;1,8;2,1;2,4 | B50: =$P50*MIN($Q50,B$3) -> 0.3 | C50: =$P50*MIN($Q50,C$3) -> 0.6 | D50: =$P50*MIN($Q50,D$3) -> 0.9 | E50: =$P50*MIN($Q50,E$3) -> 1.2 | F50: =$P50*MIN($Q50,F$3) -> 1.5 | G50: =$P50*MIN($Q50,G$3) -> 1.8 | H50: =$P50*MIN($Q50,H$3) -> 2.1 | I50: =$P50*MIN($Q50,I$3) -> 2.4 | J50: base_install_request | K50: base.group_user | M50: =INDEX('Pivot Analysis'!A:B,MATCH(J50,'Pivot Analysis'!B:B,0),1) -> 3 | N50: =INDEX(Cloc!E:F,MATCH(J50,Cloc!F:F,0),1) -> 15.72 | O50: =IFERROR(IFERROR(IF(L50<>"",L50,M50),N50),$O$1) -> 3 | P50: =O50/Q50 -> 0.3 | Q50: =MAX(1,SUMPRODUCT($R$1:$AD$1,R50:AD50)) -> 10 | S50: 1 | X50: =IF(SUM(R50:W50)=0,VLOOKUP(J50,#REF!,1,0),"") | Y50: =IF(SUM(R50:X50)>0,"",VLOOKUP(J50,'Apps-from-odoo'!A:A,1,0))
A51: =J51&";"&K51&";"&B51&";"&C51&";"&D51&";"&E51&";"&F51&";"&G51&";"&H51&";"&I51 -> base_setup;base.group_user;0;0;0;0;0;0;0;0 | B51: =$P51*MIN($Q51,B$3) -> 0 | C51: =$P51*MIN($Q51,C$3) -> 0 | D51: =$P51*MIN($Q51,D$3) -> 0 | E51: =$P51*MIN($Q51,E$3) -> 0 | F51: =$P51*MIN($Q51,F$3) -> 0 | G51: =$P51*MIN($Q51,G$3) -> 0 | H51: =$P51*MIN($Q51,H$3) -> 0 | I51: =$P51*MIN($Q51,I$3) -> 0 | J51: base_setup | K51: base.group_user | M51: =INDEX('Pivot Analysis'!A:B,MATCH(J51,'Pivot Analysis'!B:B,0),1) -> 0 | N51: =INDEX(Cloc!E:F,MATCH(J51,Cloc!F:F,0),1) -> 30.54 | O51: =IFERROR(IFERROR(IF(L51<>"",L51,M51),N51),$O$1) -> 0 | P51: =O51/Q51 -> 0 | Q51: =MAX(1,SUMPRODUCT($R$1:$AD$1,R51:AD51)) -> 1000 | R51: 1 | X51: =IF(SUM(R51:W51)=0,VLOOKUP(J51,#REF!,1,0),"") | Y51: =IF(SUM(R51:X51)>0,"",VLOOKUP(J51,'Apps-from-odoo'!A:A,1,0))
A52: =J52&";"&K52&";"&B52&";"&C52&";"&D52&";"&E52&";"&F52&";"&G52&";"&H52&";"&I52 -> base_sparse_field;base.group_user;0;0;0;0;0;0;0;0 | B52: =$P52*MIN($Q52,B$3) -> 0 | C52: =$P52*MIN($Q52,C$3) -> 0 | D52: =$P52*MIN($Q52,D$3) -> 0 | E52: =$P52*MIN($Q52,E$3) -> 0 | F52: =$P52*MIN($Q52,F$3) -> 0 | G52: =$P52*MIN($Q52,G$3) -> 0 | H52: =$P52*MIN($Q52,H$3) -> 0 | I52: =$P52*MIN($Q52,I$3) -> 0 | J52: base_sparse_field | K52: base.group_user | M52: =INDEX('Pivot Analysis'!A:B,MATCH(J52,'Pivot Analysis'!B:B,0),1) -> 0 | N52: =INDEX(Cloc!E:F,MATCH(J52,Cloc!F:F,0),1) -> #N/A | O52: =IFERROR(IFERROR(IF(L52<>"",L52,M52),N52),$O$1) -> 0 | P52: =O52/Q52 -> 0 | Q52: =MAX(1,SUMPRODUCT($R$1:$AD$1,R52:AD52)) -> 1
A53: =J53&";"&K53&";"&B53&";"&C53&";"&D53&";"&E53&";"&F53&";"&G53&";"&H53&";"&I53 -> base_unique_code;base.group_user;1000;1000;1000;1000;1000;1000;1000;1000 | B53: =$P53*MIN($Q53,B$3) -> 1000 | C53: =$P53*MIN($Q53,C$3) -> 1000 | D53: =$P53*MIN($Q53,D$3) -> 1000 | E53: =$P53*MIN($Q53,E$3) -> 1000 | F53: =$P53*MIN($Q53,F$3) -> 1000 | G53: =$P53*MIN($Q53,G$3) -> 1000 | H53: =$P53*MIN($Q53,H$3) -> 1000 | I53: =$P53*MIN($Q53,I$3) -> 1000 | J53: base_unique_code | K53: base.group_user | M53: =INDEX('Pivot Analysis'!A:B,MATCH(J53,'Pivot Analysis'!B:B,0),1) -> #N/A | N53: =INDEX(Cloc!E:F,MATCH(J53,Cloc!F:F,0),1) -> #N/A | O53: =IFERROR(IFERROR(IF(L53<>"",L53,M53),N53),$O$1) -> 1000 | P53: =O53/Q53 -> 1000 | Q53: =MAX(1,SUMPRODUCT($R$1:$AD$1,R53:AD53)) -> 1 | AB53: 1
A54: =J54&";"&K54&";"&B54&";"&C54&";"&D54&";"&E54&";"&F54&";"&G54&";"&H54&";"&I54 -> base_vat;base.group_user;0;0;0;0;0;0;0;0 | B54: =$P54*MIN($Q54,B$3) -> 0 | C54: =$P54*MIN($Q54,C$3) -> 0 | D54: =$P54*MIN($Q54,D$3) -> 0 | E54: =$P54*MIN($Q54,E$3) -> 0 | F54: =$P54*MIN($Q54,F$3) -> 0 | G54: =$P54*MIN($Q54,G$3) -> 0 | H54: =$P54*MIN($Q54,H$3) -> 0 | I54: =$P54*MIN($Q54,I$3) -> 0 | J54: base_vat | K54: base.group_user | M54: =INDEX('Pivot Analysis'!A:B,MATCH(J54,'Pivot Analysis'!B:B,0),1) -> 0 | N54: =INDEX(Cloc!E:F,MATCH(J54,Cloc!F:F,0),1) -> #N/A | O54: =IFERROR(IFERROR(IF(L54<>"",L54,M54),N54),$O$1) -> 0 | P54: =O54/Q54 -> 0 | Q54: =MAX(1,SUMPRODUCT($R$1:$AD$1,R54:AD54)) -> 1
A55: =J55&";"&K55&";"&B55&";"&C55&";"&D55&";"&E55&";"&F55&";"&G55&";"&H55&";"&I55 -> board;base.group_user;0;0;0;0;0;0;0;0 | B55: =$P55*MIN($Q55,B$3) -> 0 | C55: =$P55*MIN($Q55,C$3) -> 0 | D55: =$P55*MIN($Q55,D$3) -> 0 | E55: =$P55*MIN($Q55,E$3) -> 0 | F55: =$P55*MIN($Q55,F$3) -> 0 | G55: =$P55*MIN($Q55,G$3) -> 0 | H55: =$P55*MIN($Q55,H$3) -> 0 | I55: =$P55*MIN($Q55,I$3) -> 0 | J55: board | K55: base.group_user | M55: =INDEX('Pivot Analysis'!A:B,MATCH(J55,'Pivot Analysis'!B:B,0),1) -> 0 | N55: =INDEX(Cloc!E:F,MATCH(J55,Cloc!F:F,0),1) -> #N/A | O55: =IFERROR(IFERROR(IF(L55<>"",L55,M55),N55),$O$1) -> 0 | P55: =O55/Q55 -> 0 | Q55: =MAX(1,SUMPRODUCT($R$1:$AD$1,R55:AD55)) -> 1
A56: =J56&";"&K56&";"&B56&";"&C56&";"&D56&";"&E56&";"&F56&";"&G56&";"&H56&";"&I56 -> bus;base.group_user;0;0;0;0;0;0;0;0 | B56: =$P56*MIN($Q56,B$3) -> 0 | C56: =$P56*MIN($Q56,C$3) -> 0 | D56: =$P56*MIN($Q56,D$3) -> 0 | E56: =$P56*MIN($Q56,E$3) -> 0 | F56: =$P56*MIN($Q56,F$3) -> 0 | G56: =$P56*MIN($Q56,G$3) -> 0 | H56: =$P56*MIN($Q56,H$3) -> 0 | I56: =$P56*MIN($Q56,I$3) -> 0 | J56: bus | K56: base.group_user | M56: =INDEX('Pivot Analysis'!A:B,MATCH(J56,'Pivot Analysis'!B:B,0),1) -> 0 | N56: =INDEX(Cloc!E:F,MATCH(J56,Cloc!F:F,0),1) -> 206.1 | O56: =IFERROR(IFERROR(IF(L56<>"",L56,M56),N56),$O$1) -> 0 | P56: =O56/Q56 -> 0 | Q56: =MAX(1,SUMPRODUCT($R$1:$AD$1,R56:AD56)) -> 1000 | R56: 1 | X56: =IF(SUM(R56:W56)=0,VLOOKUP(J56,#REF!,1,0),"") | Y56: =IF(SUM(R56:X56)>0,"",VLOOKUP(J56,'Apps-from-odoo'!A:A,1,0))
A57: =J57&";"&K57&";"&B57&";"&C57&";"&D57&";"&E57&";"&F57&";"&G57&";"&H57&";"&I57 -> calendar;base.group_user;0,96;1,92;2,88;3,84;4,8;4,8;4,8;4,8 | B57: =$P57*MIN($Q57,B$3) -> 0.96 | C57: =$P57*MIN($Q57,C$3) -> 1.92 | D57: =$P57*MIN($Q57,D$3) -> 2.88 | E57: =$P57*MIN($Q57,E$3) -> 3.84 | F57: =$P57*MIN($Q57,F$3) -> 4.8 | G57: =$P57*MIN($Q57,G$3) -> 4.8 | H57: =$P57*MIN($Q57,H$3) -> 4.8 | I57: =$P57*MIN($Q57,I$3) -> 4.8 | J57: calendar | K57: base.group_user | M57: =INDEX('Pivot Analysis'!A:B,MATCH(J57,'Pivot Analysis'!B:B,0),1) -> 4.8 | N57: =INDEX(Cloc!E:F,MATCH(J57,Cloc!F:F,0),1) -> 390.72 | O57: =IFERROR(IFERROR(IF(L57<>"",L57,M57),N57),$O$1) -> 4.8 | P57: =O57/Q57 -> 0.96 | Q57: =MAX(1,SUMPRODUCT($R$1:$AD$1,R57:AD57)) -> 5 | W57: 1 | X57: =IF(SUM(R57:W57)=0,VLOOKUP(J57,#REF!,1,0),"") | Y57: =IF(SUM(R57:X57)>0,"",VLOOKUP(J57,'Apps-from-odoo'!A:A,1,0))
A58: =J58&";"&K58&";"&B58&";"&C58&";"&D58&";"&E58&";"&F58&";"&G58&";"&H58&";"&I58 -> calendar_sms;base.group_user;0;0;0;0;0;0;0;0 | B58: =$P58*MIN($Q58,B$3) -> 0 | C58: =$P58*MIN($Q58,C$3) -> 0 | D58: =$P58*MIN($Q58,D$3) -> 0 | E58: =$P58*MIN($Q58,E$3) -> 0 | F58: =$P58*MIN($Q58,F$3) -> 0 | G58: =$P58*MIN($Q58,G$3) -> 0 | H58: =$P58*MIN($Q58,H$3) -> 0 | I58: =$P58*MIN($Q58,I$3) -> 0 | J58: calendar_sms | K58: base.group_user | M58: =INDEX('Pivot Analysis'!A:B,MATCH(J58,'Pivot Analysis'!B:B,0),1) -> 0 | N58: =INDEX(Cloc!E:F,MATCH(J58,Cloc!F:F,0),1) -> 10.26 | O58: =IFERROR(IFERROR(IF(L58<>"",L58,M58),N58),$O$1) -> 0 | P58: =O58/Q58 -> 0 | Q58: =MAX(1,SUMPRODUCT($R$1:$AD$1,R58:AD58)) -> 5 | W58: 1 | X58: =IF(SUM(R58:W58)=0,VLOOKUP(J58,#REF!,1,0),"") | Y58: =IF(SUM(R58:X58)>0,"",VLOOKUP(J58,'Apps-from-odoo'!A:A,1,0))
A59: =J59&";"&K59&";"&B59&";"&C59&";"&D59&";"&E59&";"&F59&";"&G59&";"&H59&";"&I59 -> certificate;base.group_user;1000;1000;1000;1000;1000;1000;1000;1000 | B59: =$P59*MIN($Q59,B$3) -> 1000 | C59: =$P59*MIN($Q59,C$3) -> 1000 | D59: =$P59*MIN($Q59,D$3) -> 1000 | E59: =$P59*MIN($Q59,E$3) -> 1000 | F59: =$P59*MIN($Q59,F$3) -> 1000 | G59: =$P59*MIN($Q59,G$3) -> 1000 | H59: =$P59*MIN($Q59,H$3) -> 1000 | I59: =$P59*MIN($Q59,I$3) -> 1000 | J59: certificate | K59: base.group_user | M59: =INDEX('Pivot Analysis'!A:B,MATCH(J59,'Pivot Analysis'!B:B,0),1) -> #N/A | N59: =INDEX(Cloc!E:F,MATCH(J59,Cloc!F:F,0),1) -> #N/A | O59: =IFERROR(IFERROR(IF(L59<>"",L59,M59),N59),$O$1) -> 1000 | P59: =O59/Q59 -> 1000 | Q59: =MAX(1,SUMPRODUCT($R$1:$AD$1,R59:AD59)) -> 1 | Z59: 1
A60: =J60&";"&K60&";"&B60&";"&C60&";"&D60&";"&E60&";"&F60&";"&G60&";"&H60&";"&I60 -> cloud_storage;base.group_user;1000;1000;1000;1000;1000;1000;1000;1000 | B60: =$P60*MIN($Q60,B$3) -> 1000 | C60: =$P60*MIN($Q60,C$3) -> 1000 | D60: =$P60*MIN($Q60,D$3) -> 1000 | E60: =$P60*MIN($Q60,E$3) -> 1000 | F60: =$P60*MIN($Q60,F$3) -> 1000 | G60: =$P60*MIN($Q60,G$3) -> 1000 | H60: =$P60*MIN($Q60,H$3) -> 1000 | I60: =$P60*MIN($Q60,I$3) -> 1000 | J60: cloud_storage | K60: base.group_user | M60: =INDEX('Pivot Analysis'!A:B,MATCH(J60,'Pivot Analysis'!B:B,0),1) -> #N/A | N60: =INDEX(Cloc!E:F,MATCH(J60,Cloc!F:F,0),1) -> #N/A | O60: =IFERROR(IFERROR(IF(L60<>"",L60,M60),N60),$O$1) -> 1000 | P60: =O60/Q60 -> 1000 | Q60: =MAX(1,SUMPRODUCT($R$1:$AD$1,R60:AD60)) -> 1 | Z60: 1
A61: =J61&";"&K61&";"&B61&";"&C61&";"&D61&";"&E61&";"&F61&";"&G61&";"&H61&";"&I61 -> cloud_storage_azure;base.group_user;1000;1000;1000;1000;1000;1000;1000;1000 | B61: =$P61*MIN($Q61,B$3) -> 1000 | C61: =$P61*MIN($Q61,C$3) -> 1000 | D61: =$P61*MIN($Q61,D$3) -> 1000 | E61: =$P61*MIN($Q61,E$3) -> 1000 | F61: =$P61*MIN($Q61,F$3) -> 1000 | G61: =$P61*MIN($Q61,G$3) -> 1000 | H61: =$P61*MIN($Q61,H$3) -> 1000 | I61: =$P61*MIN($Q61,I$3) -> 1000 | J61: cloud_storage_azure | K61: base.group_user | M61: =INDEX('Pivot Analysis'!A:B,MATCH(J61,'Pivot Analysis'!B:B,0),1) -> #N/A | N61: =INDEX(Cloc!E:F,MATCH(J61,Cloc!F:F,0),1) -> #N/A | O61: =IFERROR(IFERROR(IF(L61<>"",L61,M61),N61),$O$1) -> 1000 | P61: =O61/Q61 -> 1000 | Q61: =MAX(1,SUMPRODUCT($R$1:$AD$1,R61:AD61)) -> 1 | Z61: 1
A62: =J62&";"&K62&";"&B62&";"&C62&";"&D62&";"&E62&";"&F62&";"&G62&";"&H62&";"&I62 -> cloud_storage_google;base.group_user;1000;1000;1000;1000;1000;1000;1000;1000 | B62: =$P62*MIN($Q62,B$3) -> 1000 | C62: =$P62*MIN($Q62,C$3) -> 1000 | D62: =$P62*MIN($Q62,D$3) -> 1000 | E62: =$P62*MIN($Q62,E$3) -> 1000 | F62: =$P62*MIN($Q62,F$3) -> 1000 | G62: =$P62*MIN($Q62,G$3) -> 1000 | H62: =$P62*MIN($Q62,H$3) -> 1000 | I62: =$P62*MIN($Q62,I$3) -> 1000 | J62: cloud_storage_google | K62: base.group_user | M62: =INDEX('Pivot Analysis'!A:B,MATCH(J62,'Pivot Analysis'!B:B,0),1) -> #N/A | N62: =INDEX(Cloc!E:F,MATCH(J62,Cloc!F:F,0),1) -> #N/A | O62: =IFERROR(IFERROR(IF(L62<>"",L62,M62),N62),$O$1) -> 1000 | P62: =O62/Q62 -> 1000 | Q62: =MAX(1,SUMPRODUCT($R$1:$AD$1,R62:AD62)) -> 1 | Z62: 1
A63: =J63&";"&K63&";"&B63&";"&C63&";"&D63&";"&E63&";"&F63&";"&G63&";"&H63&";"&I63 -> contacts;base.group_user;0,6;1,2;1,8;2,4;3;3;3;3 | B63: =$P63*MIN($Q63,B$3) -> 0.6 | C63: =$P63*MIN($Q63,C$3) -> 1.2 | D63: =$P63*MIN($Q63,D$3) -> 1.8 | E63: =$P63*MIN($Q63,E$3) -> 2.4 | F63: =$P63*MIN($Q63,F$3) -> 3 | G63: =$P63*MIN($Q63,G$3) -> 3 | H63: =$P63*MIN($Q63,H$3) -> 3 | I63: =$P63*MIN($Q63,I$3) -> 3 | J63: contacts | K63: base.group_user | M63: =INDEX('Pivot Analysis'!A:B,MATCH(J63,'Pivot Analysis'!B:B,0),1) -> 3 | N63: =INDEX(Cloc!E:F,MATCH(J63,Cloc!F:F,0),1) -> 8.4 | O63: =IFERROR(IFERROR(IF(L63<>"",L63,M63),N63),$O$1) -> 3 | P63: =O63/Q63 -> 0.6 | Q63: =MAX(1,SUMPRODUCT($R$1:$AD$1,R63:AD63)) -> 5 | W63: 1 | X63: =IF(SUM(R63:W63)=0,VLOOKUP(J63,#REF!,1,0),"") | Y63: =IF(SUM(R63:X63)>0,"",VLOOKUP(J63,'Apps-from-odoo'!A:A,1,0))
A64: =J64&";"&K64&";"&B64&";"&C64&";"&D64&";"&E64&";"&F64&";"&G64&";"&H64&";"&I64 -> crm;base.group_user;1,6;3,2;4,8;4,8;4,8;4,8;4,8;4,8 | B64: =$P64*MIN($Q64,B$3) -> 1.6 | C64: =$P64*MIN($Q64,C$3) -> 3.2 | D64: =$P64*MIN($Q64,D$3) -> 4.8 | E64: =$P64*MIN($Q64,E$3) -> 4.8 | F64: =$P64*MIN($Q64,F$3) -> 4.8 | G64: =$P64*MIN($Q64,G$3) -> 4.8 | H64: =$P64*MIN($Q64,H$3) -> 4.8 | I64: =$P64*MIN($Q64,I$3) -> 4.8 | J64: crm | K64: base.group_user | M64: =INDEX('Pivot Analysis'!A:B,MATCH(J64,'Pivot Analysis'!B:B,0),1) -> 4.8 | N64: =INDEX(Cloc!E:F,MATCH(J64,Cloc!F:F,0),1) -> 556.14 | O64: =IFERROR(IFERROR(IF(L64<>"",L64,M64),N64),$O$1) -> 4.8 | P64: =O64/Q64 -> 1.6 | Q64: =MAX(1,SUMPRODUCT($R$1:$AD$1,R64:AD64)) -> 3 | Y64: 1
A65: =J65&";"&K65&";"&B65&";"&C65&";"&D65&";"&E65&";"&F65&";"&G65&";"&H65&";"&I65 -> crm_iap_enrich;base.group_user;0;0;0;0;0;0;0;0 | B65: =$P65*MIN($Q65,B$3) -> 0 | C65: =$P65*MIN($Q65,C$3) -> 0 | D65: =$P65*MIN($Q65,D$3) -> 0 | E65: =$P65*MIN($Q65,E$3) -> 0 | F65: =$P65*MIN($Q65,F$3) -> 0 | G65: =$P65*MIN($Q65,G$3) -> 0 | H65: =$P65*MIN($Q65,H$3) -> 0 | I65: =$P65*MIN($Q65,I$3) -> 0 | J65: crm_iap_enrich | K65: base.group_user | M65: =INDEX('Pivot Analysis'!A:B,MATCH(J65,'Pivot Analysis'!B:B,0),1) -> 0 | N65: =INDEX(Cloc!E:F,MATCH(J65,Cloc!F:F,0),1) -> 17.28 | O65: =IFERROR(IFERROR(IF(L65<>"",L65,M65),N65),$O$1) -> 0 | P65: =O65/Q65 -> 0 | Q65: =MAX(1,SUMPRODUCT($R$1:$AD$1,R65:AD65)) -> 3 | Y65: 1
A66: =J66&";"&K66&";"&B66&";"&C66&";"&D66&";"&E66&";"&F66&";"&G66&";"&H66&";"&I66 -> crm_iap_mine;base.group_user;10;20;30;30;30;30;30;30 | B66: =$P66*MIN($Q66,B$3) -> 10 | C66: =$P66*MIN($Q66,C$3) -> 20 | D66: =$P66*MIN($Q66,D$3) -> 30 | E66: =$P66*MIN($Q66,E$3) -> 30 | F66: =$P66*MIN($Q66,F$3) -> 30 | G66: =$P66*MIN($Q66,G$3) -> 30 | H66: =$P66*MIN($Q66,H$3) -> 30 | I66: =$P66*MIN($Q66,I$3) -> 30 | J66: crm_iap_mine | K66: base.group_user | M66: =INDEX('Pivot Analysis'!A:B,MATCH(J66,'Pivot Analysis'!B:B,0),1) -> 30 | N66: =INDEX(Cloc!E:F,MATCH(J66,Cloc!F:F,0),1) -> 54.84 | O66: =IFERROR(IFERROR(IF(L66<>"",L66,M66),N66),$O$1) -> 30 | P66: =O66/Q66 -> 10 | Q66: =MAX(1,SUMPRODUCT($R$1:$AD$1,R66:AD66)) -> 3 | Y66: 1
A67: =J67&";"&K67&";"&B67&";"&C67&";"&D67&";"&E67&";"&F67&";"&G67&";"&H67&";"&I67 -> crm_livechat;base.group_user;0;0;0;0;0;0;0;0 | B67: =$P67*MIN($Q67,B$3) -> 0 | C67: =$P67*MIN($Q67,C$3) -> 0 | D67: =$P67*MIN($Q67,D$3) -> 0 | E67: =$P67*MIN($Q67,E$3) -> 0 | F67: =$P67*MIN($Q67,F$3) -> 0 | G67: =$P67*MIN($Q67,G$3) -> 0 | H67: =$P67*MIN($Q67,H$3) -> 0 | I67: =$P67*MIN($Q67,I$3) -> 0 | J67: crm_livechat | K67: base.group_user | M67: =INDEX('Pivot Analysis'!A:B,MATCH(J67,'Pivot Analysis'!B:B,0),1) -> 0 | N67: =INDEX(Cloc!E:F,MATCH(J67,Cloc!F:F,0),1) -> 15.18 | O67: =IFERROR(IFERROR(IF(L67<>"",L67,M67),N67),$O$1) -> 0 | P67: =O67/Q67 -> 0 | Q67: =MAX(1,SUMPRODUCT($R$1:$AD$1,R67:AD67)) -> 3 | Y67: 1
A68: =J68&";"&K68&";"&B68&";"&C68&";"&D68&";"&E68&";"&F68&";"&G68&";"&H68&";"&I68 -> crm_mail_plugin;base.group_user;33;33;33;33;33;33;33;33 | B68: =$P68*MIN($Q68,B$3) -> 33 | C68: =$P68*MIN($Q68,C$3) -> 33 | D68: =$P68*MIN($Q68,D$3) -> 33 | E68: =$P68*MIN($Q68,E$3) -> 33 | F68: =$P68*MIN($Q68,F$3) -> 33 | G68: =$P68*MIN($Q68,G$3) -> 33 | H68: =$P68*MIN($Q68,H$3) -> 33 | I68: =$P68*MIN($Q68,I$3) -> 33 | J68: crm_mail_plugin | K68: base.group_user | M68: =INDEX('Pivot Analysis'!A:B,MATCH(J68,'Pivot Analysis'!B:B,0),1) -> 33 | N68: =INDEX(Cloc!E:F,MATCH(J68,Cloc!F:F,0),1) -> #N/A | O68: =IFERROR(IFERROR(IF(L68<>"",L68,M68),N68),$O$1) -> 33 | P68: =O68/Q68 -> 33 | Q68: =MAX(1,SUMPRODUCT($R$1:$AD$1,R68:AD68)) -> 1
A69: =J69&";"&K69&";"&B69&";"&C69&";"&D69&";"&E69&";"&F69&";"&G69&";"&H69&";"&I69 -> crm_sms;base.group_user;1;2;3;3;3;3;3;3 | B69: =$P69*MIN($Q69,B$3) -> 1 | C69: =$P69*MIN($Q69,C$3) -> 2 | D69: =$P69*MIN($Q69,D$3) -> 3 | E69: =$P69*MIN($Q69,E$3) -> 3 | F69: =$P69*MIN($Q69,F$3) -> 3 | G69: =$P69*MIN($Q69,G$3) -> 3 | H69: =$P69*MIN($Q69,H$3) -> 3 | I69: =$P69*MIN($Q69,I$3) -> 3 | J69: crm_sms | K69: base.group_user | M69: =INDEX('Pivot Analysis'!A:B,MATCH(J69,'Pivot Analysis'!B:B,0),1) -> 3 | N69: =INDEX(Cloc!E:F,MATCH(J69,Cloc!F:F,0),1) -> 3.9 | O69: =IFERROR(IFERROR(IF(L69<>"",L69,M69),N69),$O$1) -> 3 | P69: =O69/Q69 -> 1 | Q69: =MAX(1,SUMPRODUCT($R$1:$AD$1,R69:AD69)) -> 3 | Y69: 1
A70: =J70&";"&K70&";"&B70&";"&C70&";"&D70&";"&E70&";"&F70&";"&G70&";"&H70&";"&I70 -> crm_unique_code;base.group_user;1000;1000;1000;1000;1000;1000;1000;1000 | B70: =$P70*MIN($Q70,B$3) -> 1000 | C70: =$P70*MIN($Q70,C$3) -> 1000 | D70: =$P70*MIN($Q70,D$3) -> 1000 | E70: =$P70*MIN($Q70,E$3) -> 1000 | F70: =$P70*MIN($Q70,F$3) -> 1000 | G70: =$P70*MIN($Q70,G$3) -> 1000 | H70: =$P70*MIN($Q70,H$3) -> 1000 | I70: =$P70*MIN($Q70,I$3) -> 1000 | J70: crm_unique_code | K70: base.group_user | M70: =INDEX('Pivot Analysis'!A:B,MATCH(J70,'Pivot Analysis'!B:B,0),1) -> #N/A | N70: =INDEX(Cloc!E:F,MATCH(J70,Cloc!F:F,0),1) -> #N/A | O70: =IFERROR(IFERROR(IF(L70<>"",L70,M70),N70),$O$1) -> 1000 | P70: =O70/Q70 -> 1000 | Q70: =MAX(1,SUMPRODUCT($R$1:$AD$1,R70:AD70)) -> 1 | AB70: 1
A71: =J71&";"&K71&";"&B71&";"&C71&";"&D71&";"&E71&";"&F71&";"&G71&";"&H71&";"&I71 -> data_recycle;base.group_user;0;0;0;0;0;0;0;0 | B71: =$P71*MIN($Q71,B$3) -> 0 | C71: =$P71*MIN($Q71,C$3) -> 0 | D71: =$P71*MIN($Q71,D$3) -> 0 | E71: =$P71*MIN($Q71,E$3) -> 0 | F71: =$P71*MIN($Q71,F$3) -> 0 | G71: =$P71*MIN($Q71,G$3) -> 0 | H71: =$P71*MIN($Q71,H$3) -> 0 | I71: =$P71*MIN($Q71,I$3) -> 0 | J71: data_recycle | K71: base.group_user | M71: =INDEX('Pivot Analysis'!A:B,MATCH(J71,'Pivot Analysis'!B:B,0),1) -> 0 | N71: =INDEX(Cloc!E:F,MATCH(J71,Cloc!F:F,0),1) -> 35.34 | O71: =IFERROR(IFERROR(IF(L71<>"",L71,M71),N71),$O$1) -> 0 | P71: =O71/Q71 -> 0 | Q71: =MAX(1,SUMPRODUCT($R$1:$AD$1,R71:AD71)) -> 3 | Y71: 1
A72: =J72&";"&K72&";"&B72&";"&C72&";"&D72&";"&E72&";"&F72&";"&G72&";"&H72&";"&I72 -> delivery;base.group_user;3;6;9;12;15;15;15;15 | B72: =$P72*MIN($Q72,B$3) -> 3 | C72: =$P72*MIN($Q72,C$3) -> 6 | D72: =$P72*MIN($Q72,D$3) -> 9 | E72: =$P72*MIN($Q72,E$3) -> 12 | F72: =$P72*MIN($Q72,F$3) -> 15 | G72: =$P72*MIN($Q72,G$3) -> 15 | H72: =$P72*MIN($Q72,H$3) -> 15 | I72: =$P72*MIN($Q72,I$3) -> 15 | J72: delivery | K72: base.group_user | M72: =INDEX('Pivot Analysis'!A:B,MATCH(J72,'Pivot Analysis'!B:B,0),1) -> 15 | N72: =INDEX(Cloc!E:F,MATCH(J72,Cloc!F:F,0),1) -> 148.86 | O72: =IFERROR(IFERROR(IF(L72<>"",L72,M72),N72),$O$1) -> 15 | P72: =O72/Q72 -> 3 | Q72: =MAX(1,SUMPRODUCT($R$1:$AD$1,R72:AD72)) -> 5 | X72: 1 | Y72: =IF(SUM(R72:X72)>0,"",VLOOKUP(J72,'Apps-from-odoo'!A:A,1,0))
A73: =J73&";"&K73&";"&B73&";"&C73&";"&D73&";"&E73&";"&F73&";"&G73&";"&H73&";"&I73 -> delivery_mondialrelay;base.group_user;0;0;0;0;0;0;0;0 | B73: =$P73*MIN($Q73,B$3) -> 0 | C73: =$P73*MIN($Q73,C$3) -> 0 | D73: =$P73*MIN($Q73,D$3) -> 0 | E73: =$P73*MIN($Q73,E$3) -> 0 | F73: =$P73*MIN($Q73,F$3) -> 0 | G73: =$P73*MIN($Q73,G$3) -> 0 | H73: =$P73*MIN($Q73,H$3) -> 0 | I73: =$P73*MIN($Q73,I$3) -> 0 | J73: delivery_mondialrelay | K73: base.group_user | M73: =INDEX('Pivot Analysis'!A:B,MATCH(J73,'Pivot Analysis'!B:B,0),1) -> 0 | N73: =INDEX(Cloc!E:F,MATCH(J73,Cloc!F:F,0),1) -> #N/A | O73: =IFERROR(IFERROR(IF(L73<>"",L73,M73),N73),$O$1) -> 0 | P73: =O73/Q73 -> 0 | Q73: =MAX(1,SUMPRODUCT($R$1:$AD$1,R73:AD73)) -> 1
A74: =J74&";"&K74&";"&B74&";"&C74&";"&D74&";"&E74&";"&F74&";"&G74&";"&H74&";"&I74 -> delivery_stock_picking_batch;base.group_user;0;0;0;0;0;0;0;0 | B74: =$P74*MIN($Q74,B$3) -> 0 | C74: =$P74*MIN($Q74,C$3) -> 0 | D74: =$P74*MIN($Q74,D$3) -> 0 | E74: =$P74*MIN($Q74,E$3) -> 0 | F74: =$P74*MIN($Q74,F$3) -> 0 | G74: =$P74*MIN($Q74,G$3) -> 0 | H74: =$P74*MIN($Q74,H$3) -> 0 | I74: =$P74*MIN($Q74,I$3) -> 0 | J74: delivery_stock_picking_batch | K74: base.group_user | M74: =INDEX('Pivot Analysis'!A:B,MATCH(J74,'Pivot Analysis'!B:B,0),1) -> 0 | N74: =INDEX(Cloc!E:F,MATCH(J74,Cloc!F:F,0),1) -> #N/A | O74: =IFERROR(IFERROR(IF(L74<>"",L74,M74),N74),$O$1) -> 0 | P74: =O74/Q74 -> 0 | Q74: =MAX(1,SUMPRODUCT($R$1:$AD$1,R74:AD74)) -> 1
A75: =J75&";"&K75&";"&B75&";"&C75&";"&D75&";"&E75&";"&F75&";"&G75&";"&H75&";"&I75 -> digest;base.group_user;0;0;0;0;0;0;0;0 | B75: =$P75*MIN($Q75,B$3) -> 0 | C75: =$P75*MIN($Q75,C$3) -> 0 | D75: =$P75*MIN($Q75,D$3) -> 0 | E75: =$P75*MIN($Q75,E$3) -> 0 | F75: =$P75*MIN($Q75,F$3) -> 0 | G75: =$P75*MIN($Q75,G$3) -> 0 | H75: =$P75*MIN($Q75,H$3) -> 0 | I75: =$P75*MIN($Q75,I$3) -> 0 | J75: digest | K75: base.group_user | M75: =INDEX('Pivot Analysis'!A:B,MATCH(J75,'Pivot Analysis'!B:B,0),1) -> 0 | N75: =INDEX(Cloc!E:F,MATCH(J75,Cloc!F:F,0),1) -> 87.18 | O75: =IFERROR(IFERROR(IF(L75<>"",L75,M75),N75),$O$1) -> 0 | P75: =O75/Q75 -> 0 | Q75: =MAX(1,SUMPRODUCT($R$1:$AD$1,R75:AD75)) -> 10 | U75: 1 | X75: =IF(SUM(R75:W75)=0,VLOOKUP(J75,#REF!,1,0),"") | Y75: =IF(SUM(R75:X75)>0,"",VLOOKUP(J75,'Apps-from-odoo'!A:A,1,0))
A76: =J76&";"&K76&";"&B76&";"&C76&";"&D76&";"&E76&";"&F76&";"&G76&";"&H76&";"&I76 -> dms;base.group_user;1000;1000;1000;1000;1000;1000;1000;1000 | B76: =$P76*MIN($Q76,B$3) -> 1000 | C76: =$P76*MIN($Q76,C$3) -> 1000 | D76: =$P76*MIN($Q76,D$3) -> 1000 | E76: =$P76*MIN($Q76,E$3) -> 1000 | F76: =$P76*MIN($Q76,F$3) -> 1000 | G76: =$P76*MIN($Q76,G$3) -> 1000 | H76: =$P76*MIN($Q76,H$3) -> 1000 | I76: =$P76*MIN($Q76,I$3) -> 1000 | J76: dms | K76: base.group_user | M76: =INDEX('Pivot Analysis'!A:B,MATCH(J76,'Pivot Analysis'!B:B,0),1) -> #N/A | N76: =INDEX(Cloc!E:F,MATCH(J76,Cloc!F:F,0),1) -> #N/A | O76: =IFERROR(IFERROR(IF(L76<>"",L76,M76),N76),$O$1) -> 1000 | P76: =O76/Q76 -> 1000 | Q76: =MAX(1,SUMPRODUCT($R$1:$AD$1,R76:AD76)) -> 1 | AA76: 1
A77: =J77&";"&K77&";"&B77&";"&C77&";"&D77&";"&E77&";"&F77&";"&G77&";"&H77&";"&I77 -> dms_attachment_link;base.group_user;1000;1000;1000;1000;1000;1000;1000;1000 | B77: =$P77*MIN($Q77,B$3) -> 1000 | C77: =$P77*MIN($Q77,C$3) -> 1000 | D77: =$P77*MIN($Q77,D$3) -> 1000 | E77: =$P77*MIN($Q77,E$3) -> 1000 | F77: =$P77*MIN($Q77,F$3) -> 1000 | G77: =$P77*MIN($Q77,G$3) -> 1000 | H77: =$P77*MIN($Q77,H$3) -> 1000 | I77: =$P77*MIN($Q77,I$3) -> 1000 | J77: dms_attachment_link | K77: base.group_user | M77: =INDEX('Pivot Analysis'!A:B,MATCH(J77,'Pivot Analysis'!B:B,0),1) -> #N/A | N77: =INDEX(Cloc!E:F,MATCH(J77,Cloc!F:F,0),1) -> #N/A | O77: =IFERROR(IFERROR(IF(L77<>"",L77,M77),N77),$O$1) -> 1000 | P77: =O77/Q77 -> 1000 | Q77: =MAX(1,SUMPRODUCT($R$1:$AD$1,R77:AD77)) -> 1 | AA77: 1
A78: =J78&";"&K78&";"&B78&";"&C78&";"&D78&";"&E78&";"&F78&";"&G78&";"&H78&";"&I78 -> dms_user_role;base.group_user;1000;1000;1000;1000;1000;1000;1000;1000 | B78: =$P78*MIN($Q78,B$3) -> 1000 | C78: =$P78*MIN($Q78,C$3) -> 1000 | D78: =$P78*MIN($Q78,D$3) -> 1000 | E78: =$P78*MIN($Q78,E$3) -> 1000 | F78: =$P78*MIN($Q78,F$3) -> 1000 | G78: =$P78*MIN($Q78,G$3) -> 1000 | H78: =$P78*MIN($Q78,H$3) -> 1000 | I78: =$P78*MIN($Q78,I$3) -> 1000 | J78: dms_user_role | K78: base.group_user | M78: =INDEX('Pivot Analysis'!A:B,MATCH(J78,'Pivot Analysis'!B:B,0),1) -> #N/A | N78: =INDEX(Cloc!E:F,MATCH(J78,Cloc!F:F,0),1) -> #N/A | O78: =IFERROR(IFERROR(IF(L78<>"",L78,M78),N78),$O$1) -> 1000 | P78: =O78/Q78 -> 1000 | Q78: =MAX(1,SUMPRODUCT($R$1:$AD$1,R78:AD78)) -> 1 | AA78: 1
A79: =J79&";"&K79&";"&B79&";"&C79&";"&D79&";"&E79&";"&F79&";"&G79&";"&H79&";"&I79 -> event;base.group_user;13,92;27,84;41,76;55,68;69,6;69,6;69,6;69,6 | B79: =$P79*MIN($Q79,B$3) -> 13.92 | C79: =$P79*MIN($Q79,C$3) -> 27.84 | D79: =$P79*MIN($Q79,D$3) -> 41.76 | E79: =$P79*MIN($Q79,E$3) -> 55.68 | F79: =$P79*MIN($Q79,F$3) -> 69.6 | G79: =$P79*MIN($Q79,G$3) -> 69.6 | H79: =$P79*MIN($Q79,H$3) -> 69.6 | I79: =$P79*MIN($Q79,I$3) -> 69.6 | J79: event | K79: base.group_user | M79: =INDEX('Pivot Analysis'!A:B,MATCH(J79,'Pivot Analysis'!B:B,0),1) -> 69.6 | N79: =INDEX(Cloc!E:F,MATCH(J79,Cloc!F:F,0),1) -> 427.44 | O79: =IFERROR(IFERROR(IF(L79<>"",L79,M79),N79),$O$1) -> 69.6 | P79: =O79/Q79 -> 13.92 | Q79: =MAX(1,SUMPRODUCT($R$1:$AD$1,R79:AD79)) -> 5 | X79: 1 | Y79: =IF(SUM(R79:X79)>0,"",VLOOKUP(J79,'Apps-from-odoo'!A:A,1,0))
A80: =J80&";"&K80&";"&B80&";"&C80&";"&D80&";"&E80&";"&F80&";"&G80&";"&H80&";"&I80 -> event_booth;base.group_user;105;105;105;105;105;105;105;105 | B80: =$P80*MIN($Q80,B$3) -> 105 | C80: =$P80*MIN($Q80,C$3) -> 105 | D80: =$P80*MIN($Q80,D$3) -> 105 | E80: =$P80*MIN($Q80,E$3) -> 105 | F80: =$P80*MIN($Q80,F$3) -> 105 | G80: =$P80*MIN($Q80,G$3) -> 105 | H80: =$P80*MIN($Q80,H$3) -> 105 | I80: =$P80*MIN($Q80,I$3) -> 105 | J80: event_booth | K80: base.group_user | M80: =INDEX('Pivot Analysis'!A:B,MATCH(J80,'Pivot Analysis'!B:B,0),1) -> 105 | N80: =INDEX(Cloc!E:F,MATCH(J80,Cloc!F:F,0),1) -> #N/A | O80: =IFERROR(IFERROR(IF(L80<>"",L80,M80),N80),$O$1) -> 105 | P80: =O80/Q80 -> 105 | Q80: =MAX(1,SUMPRODUCT($R$1:$AD$1,R80:AD80)) -> 1
A81: =J81&";"&K81&";"&B81&";"&C81&";"&D81&";"&E81&";"&F81&";"&G81&";"&H81&";"&I81 -> event_booth_sale;base.group_user;81;81;81;81;81;81;81;81 | B81: =$P81*MIN($Q81,B$3) -> 81 | C81: =$P81*MIN($Q81,C$3) -> 81 | D81: =$P81*MIN($Q81,D$3) -> 81 | E81: =$P81*MIN($Q81,E$3) -> 81 | F81: =$P81*MIN($Q81,F$3) -> 81 | G81: =$P81*MIN($Q81,G$3) -> 81 | H81: =$P81*MIN($Q81,H$3) -> 81 | I81: =$P81*MIN($Q81,I$3) -> 81 | J81: event_booth_sale | K81: base.group_user | M81: =INDEX('Pivot Analysis'!A:B,MATCH(J81,'Pivot Analysis'!B:B,0),1) -> 81 | N81: =INDEX(Cloc!E:F,MATCH(J81,Cloc!F:F,0),1) -> #N/A | O81: =IFERROR(IFERROR(IF(L81<>"",L81,M81),N81),$O$1) -> 81 | P81: =O81/Q81 -> 81 | Q81: =MAX(1,SUMPRODUCT($R$1:$AD$1,R81:AD81)) -> 1
A82: =J82&";"&K82&";"&B82&";"&C82&";"&D82&";"&E82&";"&F82&";"&G82&";"&H82&";"&I82 -> event_crm;base.group_user;3;6;9;9;9;9;9;9 | B82: =$P82*MIN($Q82,B$3) -> 3 | C82: =$P82*MIN($Q82,C$3) -> 6 | D82: =$P82*MIN($Q82,D$3) -> 9 | E82: =$P82*MIN($Q82,E$3) -> 9 | F82: =$P82*MIN($Q82,F$3) -> 9 | G82: =$P82*MIN($Q82,G$3) -> 9 | H82: =$P82*MIN($Q82,H$3) -> 9 | I82: =$P82*MIN($Q82,I$3) -> 9 | J82: event_crm | K82: base.group_user | M82: =INDEX('Pivot Analysis'!A:B,MATCH(J82,'Pivot Analysis'!B:B,0),1) -> 9 | N82: =INDEX(Cloc!E:F,MATCH(J82,Cloc!F:F,0),1) -> 63.48 | O82: =IFERROR(IFERROR(IF(L82<>"",L82,M82),N82),$O$1) -> 9 | P82: =O82/Q82 -> 3 | Q82: =MAX(1,SUMPRODUCT($R$1:$AD$1,R82:AD82)) -> 3 | Y82: 1
A83: =J83&";"&K83&";"&B83&";"&C83&";"&D83&";"&E83&";"&F83&";"&G83&";"&H83&";"&I83 -> event_crm_sale;base.group_user;11;22;33;33;33;33;33;33 | B83: =$P83*MIN($Q83,B$3) -> 11 | C83: =$P83*MIN($Q83,C$3) -> 22 | D83: =$P83*MIN($Q83,D$3) -> 33 | E83: =$P83*MIN($Q83,E$3) -> 33 | F83: =$P83*MIN($Q83,F$3) -> 33 | G83: =$P83*MIN($Q83,G$3) -> 33 | H83: =$P83*MIN($Q83,H$3) -> 33 | I83: =$P83*MIN($Q83,I$3) -> 33 | J83: event_crm_sale | K83: base.group_user | M83: =INDEX('Pivot Analysis'!A:B,MATCH(J83,'Pivot Analysis'!B:B,0),1) -> 33 | N83: =INDEX(Cloc!E:F,MATCH(J83,Cloc!F:F,0),1) -> 4.8 | O83: =IFERROR(IFERROR(IF(L83<>"",L83,M83),N83),$O$1) -> 33 | P83: =O83/Q83 -> 11 | Q83: =MAX(1,SUMPRODUCT($R$1:$AD$1,R83:AD83)) -> 3 | Y83: 1
A84: =J84&";"&K84&";"&B84&";"&C84&";"&D84&";"&E84&";"&F84&";"&G84&";"&H84&";"&I84 -> event_product;base.group_user;3,672;7,344;11,016;14,688;18,36;18,36;18,36;18,36 | B84: =$P84*MIN($Q84,B$3) -> 3.672 | C84: =$P84*MIN($Q84,C$3) -> 7.344 | D84: =$P84*MIN($Q84,D$3) -> 11.016 | E84: =$P84*MIN($Q84,E$3) -> 14.688 | F84: =$P84*MIN($Q84,F$3) -> 18.36 | G84: =$P84*MIN($Q84,G$3) -> 18.36 | H84: =$P84*MIN($Q84,H$3) -> 18.36 | I84: =$P84*MIN($Q84,I$3) -> 18.36 | J84: event_product | K84: base.group_user | M84: =INDEX('Pivot Analysis'!A:B,MATCH(J84,'Pivot Analysis'!B:B,0),1) -> #N/A | N84: =INDEX(Cloc!E:F,MATCH(J84,Cloc!F:F,0),1) -> 18.36 | O84: =IFERROR(IFERROR(IF(L84<>"",L84,M84),N84),$O$1) -> 18.36 | P84: =O84/Q84 -> 3.672 | Q84: =MAX(1,SUMPRODUCT($R$1:$AD$1,R84:AD84)) -> 5 | X84: 1 | Y84: =IF(SUM(R84:X84)>0,"",VLOOKUP(J84,'Apps-from-odoo'!A:A,1,0))
A85: =J85&";"&K85&";"&B85&";"&C85&";"&D85&";"&E85&";"&F85&";"&G85&";"&H85&";"&I85 -> event_sale;base.group_user;5,76;11,52;17,28;23,04;28,8;28,8;28,8;28,8 | B85: =$P85*MIN($Q85,B$3) -> 5.76 | C85: =$P85*MIN($Q85,C$3) -> 11.52 | D85: =$P85*MIN($Q85,D$3) -> 17.28 | E85: =$P85*MIN($Q85,E$3) -> 23.04 | F85: =$P85*MIN($Q85,F$3) -> 28.8 | G85: =$P85*MIN($Q85,G$3) -> 28.8 | H85: =$P85*MIN($Q85,H$3) -> 28.8 | I85: =$P85*MIN($Q85,I$3) -> 28.8 | J85: event_sale | K85: base.group_user | M85: =INDEX('Pivot Analysis'!A:B,MATCH(J85,'Pivot Analysis'!B:B,0),1) -> 28.8 | N85: =INDEX(Cloc!E:F,MATCH(J85,Cloc!F:F,0),1) -> 78.24 | O85: =IFERROR(IFERROR(IF(L85<>"",L85,M85),N85),$O$1) -> 28.8 | P85: =O85/Q85 -> 5.76 | Q85: =MAX(1,SUMPRODUCT($R$1:$AD$1,R85:AD85)) -> 5 | X85: 1 | Y85: =IF(SUM(R85:X85)>0,"",VLOOKUP(J85,'Apps-from-odoo'!A:A,1,0))
A86: =J86&";"&K86&";"&B86&";"&C86&";"&D86&";"&E86&";"&F86&";"&G86&";"&H86&";"&I86 -> event_sms;base.group_user;0;0;0;0;0;0;0;0 | B86: =$P86*MIN($Q86,B$3) -> 0 | C86: =$P86*MIN($Q86,C$3) -> 0 | D86: =$P86*MIN($Q86,D$3) -> 0 | E86: =$P86*MIN($Q86,E$3) -> 0 | F86: =$P86*MIN($Q86,F$3) -> 0 | G86: =$P86*MIN($Q86,G$3) -> 0 | H86: =$P86*MIN($Q86,H$3) -> 0 | I86: =$P86*MIN($Q86,I$3) -> 0 | J86: event_sms | K86: base.group_user | M86: =INDEX('Pivot Analysis'!A:B,MATCH(J86,'Pivot Analysis'!B:B,0),1) -> 0 | N86: =INDEX(Cloc!E:F,MATCH(J86,Cloc!F:F,0),1) -> 8.82 | O86: =IFERROR(IFERROR(IF(L86<>"",L86,M86),N86),$O$1) -> 0 | P86: =O86/Q86 -> 0 | Q86: =MAX(1,SUMPRODUCT($R$1:$AD$1,R86:AD86)) -> 5 | X86: 1 | Y86: =IF(SUM(R86:X86)>0,"",VLOOKUP(J86,'Apps-from-odoo'!A:A,1,0))
A87: =J87&";"&K87&";"&B87&";"&C87&";"&D87&";"&E87&";"&F87&";"&G87&";"&H87&";"&I87 -> fleet;base.group_user;3,6;7,2;10,8;14,4;18;18;18;18 | B87: =$P87*MIN($Q87,B$3) -> 3.6 | C87: =$P87*MIN($Q87,C$3) -> 7.2 | D87: =$P87*MIN($Q87,D$3) -> 10.8 | E87: =$P87*MIN($Q87,E$3) -> 14.4 | F87: =$P87*MIN($Q87,F$3) -> 18 | G87: =$P87*MIN($Q87,G$3) -> 18 | H87: =$P87*MIN($Q87,H$3) -> 18 | I87: =$P87*MIN($Q87,I$3) -> 18 | J87: fleet | K87: base.group_user | M87: =INDEX('Pivot Analysis'!A:B,MATCH(J87,'Pivot Analysis'!B:B,0),1) -> 18 | N87: =INDEX(Cloc!E:F,MATCH(J87,Cloc!F:F,0),1) -> 189.36 | O87: =IFERROR(IFERROR(IF(L87<>"",L87,M87),N87),$O$1) -> 18 | P87: =O87/Q87 -> 3.6 | Q87: =MAX(1,SUMPRODUCT($R$1:$AD$1,R87:AD87)) -> 5 | X87: 1 | Y87: =IF(SUM(R87:X87)>0,"",VLOOKUP(J87,'Apps-from-odoo'!A:A,1,0))
A88: =J88&";"&K88&";"&B88&";"&C88&";"&D88&";"&E88&";"&F88&";"&G88&";"&H88&";"&I88 -> gamification;base.group_user;0;0;0;0;0;0;0;0 | B88: =$P88*MIN($Q88,B$3) -> 0 | C88: =$P88*MIN($Q88,C$3) -> 0 | D88: =$P88*MIN($Q88,D$3) -> 0 | E88: =$P88*MIN($Q88,E$3) -> 0 | F88: =$P88*MIN($Q88,F$3) -> 0 | G88: =$P88*MIN($Q88,G$3) -> 0 | H88: =$P88*MIN($Q88,H$3) -> 0 | I88: =$P88*MIN($Q88,I$3) -> 0 | J88: gamification | K88: base.group_user | M88: =INDEX('Pivot Analysis'!A:B,MATCH(J88,'Pivot Analysis'!B:B,0),1) -> 0 | N88: =INDEX(Cloc!E:F,MATCH(J88,Cloc!F:F,0),1) -> 229.86 | O88: =IFERROR(IFERROR(IF(L88<>"",L88,M88),N88),$O$1) -> 0 | P88: =O88/Q88 -> 0 | Q88: =MAX(1,SUMPRODUCT($R$1:$AD$1,R88:AD88)) -> 3 | Y88: 1
A89: =J89&";"&K89&";"&B89&";"&C89&";"&D89&";"&E89&";"&F89&";"&G89&";"&H89&";"&I89 -> gamification_sale_crm;base.group_user;1;2;3;3;3;3;3;3 | B89: =$P89*MIN($Q89,B$3) -> 1 | C89: =$P89*MIN($Q89,C$3) -> 2 | D89: =$P89*MIN($Q89,D$3) -> 3 | E89: =$P89*MIN($Q89,E$3) -> 3 | F89: =$P89*MIN($Q89,F$3) -> 3 | G89: =$P89*MIN($Q89,G$3) -> 3 | H89: =$P89*MIN($Q89,H$3) -> 3 | I89: =$P89*MIN($Q89,I$3) -> 3 | J89: gamification_sale_crm | K89: base.group_user | M89: =INDEX('Pivot Analysis'!A:B,MATCH(J89,'Pivot Analysis'!B:B,0),1) -> 3 | N89: =INDEX(Cloc!E:F,MATCH(J89,Cloc!F:F,0),1) -> 11.58 | O89: =IFERROR(IFERROR(IF(L89<>"",L89,M89),N89),$O$1) -> 3 | P89: =O89/Q89 -> 1 | Q89: =MAX(1,SUMPRODUCT($R$1:$AD$1,R89:AD89)) -> 3 | Y89: 1
A90: =J90&";"&K90&";"&B90&";"&C90&";"&D90&";"&E90&";"&F90&";"&G90&";"&H90&";"&I90 -> google_account;base.group_user;0;0;0;0;0;0;0;0 | B90: =$P90*MIN($Q90,B$3) -> 0 | C90: =$P90*MIN($Q90,C$3) -> 0 | D90: =$P90*MIN($Q90,D$3) -> 0 | E90: =$P90*MIN($Q90,E$3) -> 0 | F90: =$P90*MIN($Q90,F$3) -> 0 | G90: =$P90*MIN($Q90,G$3) -> 0 | H90: =$P90*MIN($Q90,H$3) -> 0 | I90: =$P90*MIN($Q90,I$3) -> 0 | J90: google_account | K90: base.group_user | M90: =INDEX('Pivot Analysis'!A:B,MATCH(J90,'Pivot Analysis'!B:B,0),1) -> 0 | N90: =INDEX(Cloc!E:F,MATCH(J90,Cloc!F:F,0),1) -> #N/A | O90: =IFERROR(IFERROR(IF(L90<>"",L90,M90),N90),$O$1) -> 0 | P90: =O90/Q90 -> 0 | Q90: =MAX(1,SUMPRODUCT($R$1:$AD$1,R90:AD90)) -> 1
A91: =J91&";"&K91&";"&B91&";"&C91&";"&D91&";"&E91&";"&F91&";"&G91&";"&H91&";"&I91 -> google_calendar;base.group_user;27,3;27,3;27,3;27,3;27,3;27,3;27,3;27,3 | B91: =$P91*MIN($Q91,B$3) -> 27.3 | C91: =$P91*MIN($Q91,C$3) -> 27.3 | D91: =$P91*MIN($Q91,D$3) -> 27.3 | E91: =$P91*MIN($Q91,E$3) -> 27.3 | F91: =$P91*MIN($Q91,F$3) -> 27.3 | G91: =$P91*MIN($Q91,G$3) -> 27.3 | H91: =$P91*MIN($Q91,H$3) -> 27.3 | I91: =$P91*MIN($Q91,I$3) -> 27.3 | J91: google_calendar | K91: base.group_user | M91: =INDEX('Pivot Analysis'!A:B,MATCH(J91,'Pivot Analysis'!B:B,0),1) -> 27.3 | N91: =INDEX(Cloc!E:F,MATCH(J91,Cloc!F:F,0),1) -> #N/A | O91: =IFERROR(IFERROR(IF(L91<>"",L91,M91),N91),$O$1) -> 27.3 | P91: =O91/Q91 -> 27.3 | Q91: =MAX(1,SUMPRODUCT($R$1:$AD$1,R91:AD91)) -> 1
A92: =J92&";"&K92&";"&B92&";"&C92&";"&D92&";"&E92&";"&F92&";"&G92&";"&H92&";"&I92 -> google_gmail;base.group_user;0;0;0;0;0;0;0;0 | B92: =$P92*MIN($Q92,B$3) -> 0 | C92: =$P92*MIN($Q92,C$3) -> 0 | D92: =$P92*MIN($Q92,D$3) -> 0 | E92: =$P92*MIN($Q92,E$3) -> 0 | F92: =$P92*MIN($Q92,F$3) -> 0 | G92: =$P92*MIN($Q92,G$3) -> 0 | H92: =$P92*MIN($Q92,H$3) -> 0 | I92: =$P92*MIN($Q92,I$3) -> 0 | J92: google_gmail | K92: base.group_user | M92: =INDEX('Pivot Analysis'!A:B,MATCH(J92,'Pivot Analysis'!B:B,0),1) -> 0 | N92: =INDEX(Cloc!E:F,MATCH(J92,Cloc!F:F,0),1) -> 30.9 | O92: =IFERROR(IFERROR(IF(L92<>"",L92,M92),N92),$O$1) -> 0 | P92: =O92/Q92 -> 0 | Q92: =MAX(1,SUMPRODUCT($R$1:$AD$1,R92:AD92)) -> 10 | S92: 1 | X92: =IF(SUM(R92:W92)=0,VLOOKUP(J92,#REF!,1,0),"") | Y92: =IF(SUM(R92:X92)>0,"",VLOOKUP(J92,'Apps-from-odoo'!A:A,1,0))
A93: =J93&";"&K93&";"&B93&";"&C93&";"&D93&";"&E93&";"&F93&";"&G93&";"&H93&";"&I93 -> google_recaptcha;base.group_user;0,6;1,2;1,8;2,4;3;3;3;3 | B93: =$P93*MIN($Q93,B$3) -> 0.6 | C93: =$P93*MIN($Q93,C$3) -> 1.2 | D93: =$P93*MIN($Q93,D$3) -> 1.8 | E93: =$P93*MIN($Q93,E$3) -> 2.4 | F93: =$P93*MIN($Q93,F$3) -> 3 | G93: =$P93*MIN($Q93,G$3) -> 3 | H93: =$P93*MIN($Q93,H$3) -> 3 | I93: =$P93*MIN($Q93,I$3) -> 3 | J93: google_recaptcha | K93: base.group_user | M93: =INDEX('Pivot Analysis'!A:B,MATCH(J93,'Pivot Analysis'!B:B,0),1) -> 3 | N93: =INDEX(Cloc!E:F,MATCH(J93,Cloc!F:F,0),1) -> 18.24 | O93: =IFERROR(IFERROR(IF(L93<>"",L93,M93),N93),$O$1) -> 3 | P93: =O93/Q93 -> 0.6 | Q93: =MAX(1,SUMPRODUCT($R$1:$AD$1,R93:AD93)) -> 5 | V93: 1 | X93: =IF(SUM(R93:W93)=0,VLOOKUP(J93,#REF!,1,0),"") | Y93: =IF(SUM(R93:X93)>0,"",VLOOKUP(J93,'Apps-from-odoo'!A:A,1,0))
A94: =J94&";"&K94&";"&B94&";"&C94&";"&D94&";"&E94&";"&F94&";"&G94&";"&H94&";"&I94 -> helpdesk;base.group_user;1000;1000;1000;1000;1000;1000;1000;1000 | B94: =$P94*MIN($Q94,B$3) -> 1000 | C94: =$P94*MIN($Q94,C$3) -> 1000 | D94: =$P94*MIN($Q94,D$3) -> 1000 | E94: =$P94*MIN($Q94,E$3) -> 1000 | F94: =$P94*MIN($Q94,F$3) -> 1000 | G94: =$P94*MIN($Q94,G$3) -> 1000 | H94: =$P94*MIN($Q94,H$3) -> 1000 | I94: =$P94*MIN($Q94,I$3) -> 1000 | J94: helpdesk | K94: base.group_user | M94: =INDEX('Pivot Analysis'!A:B,MATCH(J94,'Pivot Analysis'!B:B,0),1) -> #N/A | N94: =INDEX(Cloc!E:F,MATCH(J94,Cloc!F:F,0),1) -> #N/A | O94: =IFERROR(IFERROR(IF(L94<>"",L94,M94),N94),$O$1) -> 1000 | P94: =O94/Q94 -> 1000 | Q94: =MAX(1,SUMPRODUCT($R$1:$AD$1,R94:AD94)) -> 1 | Z94: 1
A95: =J95&";"&K95&";"&B95&";"&C95&";"&D95&";"&E95&";"&F95&";"&G95&";"&H95&";"&I95 -> hr;base.group_user;9,18;18,36;27,54;36,72;45,9;45,9;45,9;45,9 | B95: =$P95*MIN($Q95,B$3) -> 9.18 | C95: =$P95*MIN($Q95,C$3) -> 18.36 | D95: =$P95*MIN($Q95,D$3) -> 27.54 | E95: =$P95*MIN($Q95,E$3) -> 36.72 | F95: =$P95*MIN($Q95,F$3) -> 45.9 | G95: =$P95*MIN($Q95,G$3) -> 45.9 | H95: =$P95*MIN($Q95,H$3) -> 45.9 | I95: =$P95*MIN($Q95,I$3) -> 45.9 | J95: hr | K95: base.group_user | M95: =INDEX('Pivot Analysis'!A:B,MATCH(J95,'Pivot Analysis'!B:B,0),1) -> 45.9 | N95: =INDEX(Cloc!E:F,MATCH(J95,Cloc!F:F,0),1) -> 361.74 | O95: =IFERROR(IFERROR(IF(L95<>"",L95,M95),N95),$O$1) -> 45.9 | P95: =O95/Q95 -> 9.18 | Q95: =MAX(1,SUMPRODUCT($R$1:$AD$1,R95:AD95)) -> 5 | W95: 1 | X95: =IF(SUM(R95:W95)=0,VLOOKUP(J95,#REF!,1,0),"") | Y95: =IF(SUM(R95:X95)>0,"",VLOOKUP(J95,'Apps-from-odoo'!A:A,1,0))
A96: =J96&";"&K96&";"&B96&";"&C96&";"&D96&";"&E96&";"&F96&";"&G96&";"&H96&";"&I96 -> hr_appraisal;base.group_user;1000;1000;1000;1000;1000;1000;1000;1000 | B96: =$P96*MIN($Q96,B$3) -> 1000 | C96: =$P96*MIN($Q96,C$3) -> 1000 | D96: =$P96*MIN($Q96,D$3) -> 1000 | E96: =$P96*MIN($Q96,E$3) -> 1000 | F96: =$P96*MIN($Q96,F$3) -> 1000 | G96: =$P96*MIN($Q96,G$3) -> 1000 | H96: =$P96*MIN($Q96,H$3) -> 1000 | I96: =$P96*MIN($Q96,I$3) -> 1000 | J96: hr_appraisal | K96: base.group_user | M96: =INDEX('Pivot Analysis'!A:B,MATCH(J96,'Pivot Analysis'!B:B,0),1) -> #N/A | N96: =INDEX(Cloc!E:F,MATCH(J96,Cloc!F:F,0),1) -> #N/A | O96: =IFERROR(IFERROR(IF(L96<>"",L96,M96),N96),$O$1) -> 1000 | P96: =O96/Q96 -> 1000 | Q96: =MAX(1,SUMPRODUCT($R$1:$AD$1,R96:AD96)) -> 1 | Z96: 1
A97: =J97&";"&K97&";"&B97&";"&C97&";"&D97&";"&E97&";"&F97&";"&G97&";"&H97&";"&I97 -> hr_attendance;base.group_user;6,6;13,2;19,8;19,8;19,8;19,8;19,8;19,8 | B97: =$P97*MIN($Q97,B$3) -> 6.6 | C97: =$P97*MIN($Q97,C$3) -> 13.2 | D97: =$P97*MIN($Q97,D$3) -> 19.8 | E97: =$P97*MIN($Q97,E$3) -> 19.8 | F97: =$P97*MIN($Q97,F$3) -> 19.8 | G97: =$P97*MIN($Q97,G$3) -> 19.8 | H97: =$P97*MIN($Q97,H$3) -> 19.8 | I97: =$P97*MIN($Q97,I$3) -> 19.8 | J97: hr_attendance | K97: base.group_user | M97: =INDEX('Pivot Analysis'!A:B,MATCH(J97,'Pivot Analysis'!B:B,0),1) -> 19.8 | N97: =INDEX(Cloc!E:F,MATCH(J97,Cloc!F:F,0),1) -> 247.56 | O97: =IFERROR(IFERROR(IF(L97<>"",L97,M97),N97),$O$1) -> 19.8 | P97: =O97/Q97 -> 6.6 | Q97: =MAX(1,SUMPRODUCT($R$1:$AD$1,R97:AD97)) -> 3 | Y97: 1
A98: =J98&";"&K98&";"&B98&";"&C98&";"&D98&";"&E98&";"&F98&";"&G98&";"&H98&";"&I98 -> hr_calendar;base.group_user;4,2;8,4;12,6;16,8;21;21;21;21 | B98: =$P98*MIN($Q98,B$3) -> 4.2 | C98: =$P98*MIN($Q98,C$3) -> 8.4 | D98: =$P98*MIN($Q98,D$3) -> 12.6 | E98: =$P98*MIN($Q98,E$3) -> 16.8 | F98: =$P98*MIN($Q98,F$3) -> 21 | G98: =$P98*MIN($Q98,G$3) -> 21 | H98: =$P98*MIN($Q98,H$3) -> 21 | I98: =$P98*MIN($Q98,I$3) -> 21 | J98: hr_calendar | K98: base.group_user | M98: =INDEX('Pivot Analysis'!A:B,MATCH(J98,'Pivot Analysis'!B:B,0),1) -> #N/A | N98: =INDEX(Cloc!E:F,MATCH(J98,Cloc!F:F,0),1) -> 21 | O98: =IFERROR(IFERROR(IF(L98<>"",L98,M98),N98),$O$1) -> 21 | P98: =O98/Q98 -> 4.2 | Q98: =MAX(1,SUMPRODUCT($R$1:$AD$1,R98:AD98)) -> 5 | W98: 1 | X98: =IF(SUM(R98:W98)=0,VLOOKUP(J98,#REF!,1,0),"") | Y98: =IF(SUM(R98:X98)>0,"",VLOOKUP(J98,'Apps-from-odoo'!A:A,1,0))
A99: =J99&";"&K99&";"&B99&";"&C99&";"&D99&";"&E99&";"&F99&";"&G99&";"&H99&";"&I99 -> hr_contract;base.group_user;0,9;1,8;2,7;3,6;4,5;4,5;4,5;4,5 | B99: =$P99*MIN($Q99,B$3) -> 0.9 | C99: =$P99*MIN($Q99,C$3) -> 1.8 | D99: =$P99*MIN($Q99,D$3) -> 2.7 | E99: =$P99*MIN($Q99,E$3) -> 3.6 | F99: =$P99*MIN($Q99,F$3) -> 4.5 | G99: =$P99*MIN($Q99,G$3) -> 4.5 | H99: =$P99*MIN($Q99,H$3) -> 4.5 | I99: =$P99*MIN($Q99,I$3) -> 4.5 | J99: hr_contract | K99: base.group_user | M99: =INDEX('Pivot Analysis'!A:B,MATCH(J99,'Pivot Analysis'!B:B,0),1) -> 4.5 | N99: =INDEX(Cloc!E:F,MATCH(J99,Cloc!F:F,0),1) -> 120.72 | O99: =IFERROR(IFERROR(IF(L99<>"",L99,M99),N99),$O$1) -> 4.5 | P99: =O99/Q99 -> 0.9 | Q99: =MAX(1,SUMPRODUCT($R$1:$AD$1,R99:AD99)) -> 5 | X99: 1 | Y99: =IF(SUM(R99:X99)>0,"",VLOOKUP(J99,'Apps-from-odoo'!A:A,1,0))
A100: =J100&";"&K100&";"&B100&";"&C100&";"&D100&";"&E100&";"&F100&";"&G100&";"&H100&";"&I100 -> hr_expense;base.group_user;2,4;4,8;7,2;9,6;12;12;12;12 | B100: =$P100*MIN($Q100,B$3) -> 2.4 | C100: =$P100*MIN($Q100,C$3) -> 4.8 | D100: =$P100*MIN($Q100,D$3) -> 7.2 | E100: =$P100*MIN($Q100,E$3) -> 9.6 | F100: =$P100*MIN($Q100,F$3) -> 12 | G100: =$P100*MIN($Q100,G$3) -> 12 | H100: =$P100*MIN($Q100,H$3) -> 12 | I100: =$P100*MIN($Q100,I$3) -> 12 | J100: hr_expense | K100: base.group_user | M100: =INDEX('Pivot Analysis'!A:B,MATCH(J100,'Pivot Analysis'!B:B,0),1) -> 12 | N100: =INDEX(Cloc!E:F,MATCH(J100,Cloc!F:F,0),1) -> 373.02 | O100: =IFERROR(IFERROR(IF(L100<>"",L100,M100),N100),$O$1) -> 12 | P100: =O100/Q100 -> 2.4 | Q100: =MAX(1,SUMPRODUCT($R$1:$AD$1,R100:AD100)) -> 5 | X100: 1 | Y100: =IF(SUM(R100:X100)>0,"",VLOOKUP(J100,'Apps-from-odoo'!A:A,1,0))
A101: =J101&";"&K101&";"&B101&";"&C101&";"&D101&";"&E101&";"&F101&";"&G101&";"&H101&";"&I101 -> hr_fleet;base.group_user;9,6;19,2;28,8;38,4;48;48;48;48 | B101: =$P101*MIN($Q101,B$3) -> 9.6 | C101: =$P101*MIN($Q101,C$3) -> 19.2 | D101: =$P101*MIN($Q101,D$3) -> 28.8 | E101: =$P101*MIN($Q101,E$3) -> 38.4 | F101: =$P101*MIN($Q101,F$3) -> 48 | G101: =$P101*MIN($Q101,G$3) -> 48 | H101: =$P101*MIN($Q101,H$3) -> 48 | I101: =$P101*MIN($Q101,I$3) -> 48 | J101: hr_fleet | K101: base.group_user | M101: =INDEX('Pivot Analysis'!A:B,MATCH(J101,'Pivot Analysis'!B:B,0),1) -> 48 | N101: =INDEX(Cloc!E:F,MATCH(J101,Cloc!F:F,0),1) -> 48.66 | O101: =IFERROR(IFERROR(IF(L101<>"",L101,M101),N101),$O$1) -> 48 | P101: =O101/Q101 -> 9.6 | Q101: =MAX(1,SUMPRODUCT($R$1:$AD$1,R101:AD101)) -> 5 | X101: 1 | Y101: =IF(SUM(R101:X101)>0,"",VLOOKUP(J101,'Apps-from-odoo'!A:A,1,0))
...

Sheet Apps-from-odoo
A1: Technical Name | B1: Exists in Apps
A2: account | B2: =VLOOKUP(A2,Apps!J:J,1,0) -> account
A3: account_check_printing | B3: =VLOOKUP(A3,Apps!J:J,1,0) -> account_check_printing
A4: account_debit_note | B4: =VLOOKUP(A4,Apps!J:J,1,0) -> account_debit_note
A5: account_edi | B5: =VLOOKUP(A5,Apps!J:J,1,0) -> account_edi
A6: account_edi_proxy_client | B6: =VLOOKUP(A6,Apps!J:J,1,0) -> account_edi_proxy_client
A7: account_edi_ubl_cii | B7: =VLOOKUP(A7,Apps!J:J,1,0) -> account_edi_ubl_cii
A8: account_edi_ubl_cii_tax_extension | B8: =VLOOKUP(A8,Apps!J:J,1,0) -> account_edi_ubl_cii_tax_extension
A9: account_fleet | B9: =VLOOKUP(A9,Apps!J:J,1,0) -> account_fleet
A10: account_payment | B10: =VLOOKUP(A10,Apps!J:J,1,0) -> account_payment
A11: account_peppol | B11: =VLOOKUP(A11,Apps!J:J,1,0) -> account_peppol
A12: account_qr_code_emv | B12: =VLOOKUP(A12,Apps!J:J,1,0) -> account_qr_code_emv
A13: account_qr_code_sepa | B13: =VLOOKUP(A13,Apps!J:J,1,0) -> account_qr_code_sepa
... A627: website_sms | B627: =VLOOKUP(A627,Apps!J:J,1,0) -> website_sms

Sheet Pivot Analysis
B1: Weight (EUR/minute) - not in 16-17 | D1: 3
A2: EUR | B2: Weight (EUR/minute) | C2: 3 | D2: 0.3
A4: EUR | B4: Summer av Minutes | C4: Kolonneetiketter
B5: Radetiketter | C5: 16-17 | D5: 17-18 | E5: Totalsum
A6: =IF(C6="",SUMPRODUCT($C$1:$D$1,$C6:$D6),SUMPRODUCT($C$2:$D$2,$C6:$D6)) -> 240 | B6: account | C6: 0 | D6: 800 | E6: 800
A7: =IF(C7="",SUMPRODUCT($C$1:$D$1,$C7:$D7),SUMPRODUCT($C$2:$D$2,$C7:$D7)) -> 0 | B7: account_audit_trail | D7: 0 | E7: 0
A8: =IF(C8="",SUMPRODUCT($C$1:$D$1,$C8:$D8),SUMPRODUCT($C$2:$D$2,$C8:$D8)) -> 7.5 | B8: account_check_printing | C8: 0 | D8: 25 | E8: 25
A9: =IF(C9="",SUMPRODUCT($C$1:$D$1,$C9:$D9),SUMPRODUCT($C$2:$D$2,$C9:$D9)) -> 34.5 | B9: account_debit_note | C9: 10 | D9: 15 | E9: 25
A10: =IF(C10="",SUMPRODUCT($C$1:$D$1,$C10:$D10),SUMPRODUCT($C$2:$D$2,$C10:$D10)) -> 0 | B10: account_edi | C10: 0 | D10: 0 | E10: 0
A11: =IF(C11="",SUMPRODUCT($C$1:$D$1,$C11:$D11),SUMPRODUCT($C$2:$D$2,$C11:$D11)) -> 81 | B11: account_edi_proxy_client | C11: 25 | D11: 20 | E11: 45
A12: =IF(C12="",SUMPRODUCT($C$1:$D$1,$C12:$D12),SUMPRODUCT($C$2:$D$2,$C12:$D12)) -> 12.3 | B12: account_edi_ubl_cii | C12: 0 | D12: 41 | E12: 41
A13: =IF(C13="",SUMPRODUCT($C$1:$D$1,$C13:$D13),SUMPRODUCT($C$2:$D$2,$C13:$D13)) -> 0 | B13: account_edi_ubl_cii_tax_extension | C13: 0 | D13: 0 | E13: 0
A14: =IF(C14="",SUMPRODUCT($C$1:$D$1,$C14:$D14),SUMPRODUCT($C$2:$D$2,$C14:$D14)) -> 7.5 | B14: account_fleet | C14: 0 | D14: 25 | E14: 25
A15: =IF(C15="",SUMPRODUCT($C$1:$D$1,$C15:$D15),SUMPRODUCT($C$2:$D$2,$C15:$D15)) -> 30 | B15: account_lock | C15: 10 | D15: 0 | E15: 10
A16: =IF(C16="",SUMPRODUCT($C$1:$D$1,$C16:$D16),SUMPRODUCT($C$2:$D$2,$C16:$D16)) -> 3.3 | B16: account_payment | C16: 0 | D16: 11 | E16: 11
A17: =IF(C17="",SUMPRODUCT($C$1:$D$1,$C17:$D17),SUMPRODUCT($C$2:$D$2,$C17:$D17)) -> 0 | B17: account_payment_invoice_online_payment_patch | C17: 0 | E17: 0
A18: =IF(C18="",SUMPRODUCT($C$1:$D$1,$C18:$D18),SUMPRODUCT($C$2:$D$2,$C18:$D18)) -> 0 | B18: account_payment_term | D18: 0 | E18: 0
A19: =IF(C19="",SUMPRODUCT($C$1:$D$1,$C19:$D19),SUMPRODUCT($C$2:$D$2,$C19:$D19)) -> 258 | B19: account_peppol | D19: 86 | E19: 86
A20: =IF(C20="",SUMPRODUCT($C$1:$D$1,$C20:$D20),SUMPRODUCT($C$2:$D$2,$C20:$D20)) -> 45 | B20: account_qr_code_emv | D20: 15 | E20: 15
A21: =IF(C21="",SUMPRODUCT($C$1:$D$1,$C21:$D21),SUMPRODUCT($C$2:$D$2,$C21:$D21)) -> 3 | B21: account_qr_code_sepa | C21: 0 | D21: 10 | E21: 10
A22: =IF(C22="",SUMPRODUCT($C$1:$D$1,$C22:$D22),SUMPRODUCT($C$2:$D$2,$C22:$D22)) -> 0 | B22: account_sequence | C22: 0 | E22: 0
A23: =IF(C23="",SUMPRODUCT($C$1:$D$1,$C23:$D23),SUMPRODUCT($C$2:$D$2,$C23:$D23)) -> 82.5 | B23: account_tax_python | C23: 25 | D23: 25 | E23: 50
A24: =IF(C24="",SUMPRODUCT($C$1:$D$1,$C24:$D24),SUMPRODUCT($C$2:$D$2,$C24:$D24)) -> 33 | B24: account_test | C24: 10 | D24: 10 | E24: 20
A25: =IF(C25="",SUMPRODUCT($C$1:$D$1,$C25:$D25),SUMPRODUCT($C$2:$D$2,$C25:$D25)) -> 0 | B25: account_update_tax_tags | C25: 0 | D25: 0 | E25: 0
A26: =IF(C26="",SUMPRODUCT($C$1:$D$1,$C26:$D26),SUMPRODUCT($C$2:$D$2,$C26:$D26)) -> 0 | B26: analytic | C26: 0 | D26: 0 | E26: 0
A27: =IF(C27="",SUMPRODUCT($C$1:$D$1,$C27:$D27),SUMPRODUCT($C$2:$D$2,$C27:$D27)) -> 0 | B27: association | C27: 0 | E27: 0
A28: =IF(C28="",SUMPRODUCT($C$1:$D$1,$C28:$D28),SUMPRODUCT($C$2:$D$2,$C28:$D28)) -> 3 | B28: attachment_indexation | C28: 0 | D28: 10 | E28: 10
A29: =IF(C29="",SUMPRODUCT($C$1:$D$1,$C29:$D29),SUMPRODUCT($C$2:$D$2,$C29:$D29)) -> 0 | B29: auth_ldap | C29: 0 | D29: 0 | E29: 0
A30: =IF(C30="",SUMPRODUCT($C$1:$D$1,$C30:$D30),SUMPRODUCT($C$2:$D$2,$C30:$D30)) -> 0 | B30: auth_oauth | C30: 0 | D30: 0 | E30: 0
A31: =IF(C31="",SUMPRODUCT($C$1:$D$1,$C31:$D31),SUMPRODUCT($C$2:$D$2,$C31:$D31)) -> 3 | B31: auth_password_policy | C31: 0 | D31: 10 | E31: 10
A32: =IF(C32="",SUMPRODUCT($C$1:$D$1,$C32:$D32),SUMPRODUCT($C$2:$D$2,$C32:$D32)) -> 33 | B32: auth_password_policy_portal | C32: 10 | D32: 10 | E32: 20
A33: =IF(C33="",SUMPRODUCT($C$1:$D$1,$C33:$D33),SUMPRODUCT($C$2:$D$2,$C33:$D33)) -> 3 | B33: auth_password_policy_signup | C33: 0 | D33: 10 | E33: 10
A34: =IF(C34="",SUMPRODUCT($C$1:$D$1,$C34:$D34),SUMPRODUCT($C$2:$D$2,$C34:$D34)) -> 0 | B34: auth_signup | C34: 0 | D34: 0 | E34: 0
A35: =IF(C35="",SUMPRODUCT($C$1:$D$1,$C35:$D35),SUMPRODUCT($C$2:$D$2,$C35:$D35)) -> 0 | B35: auth_totp | C35: 0 | D35: 0 | E35: 0
A36: =IF(C36="",SUMPRODUCT($C$1:$D$1,$C36:$D36),SUMPRODUCT($C$2:$D$2,$C36:$D36)) -> 3 | B36: auth_totp_mail | C36: 0 | D36: 10 | E36: 10
A37: =IF(C37="",SUMPRODUCT($C$1:$D$1,$C37:$D37),SUMPRODUCT($C$2:$D$2,$C37:$D37)) -> 0 | B37: auth_totp_mail_enforce | C37: 0 | D37: 0 | E37: 0
A38: =IF(C38="",SUMPRODUCT($C$1:$D$1,$C38:$D38),SUMPRODUCT($C$2:$D$2,$C38:$D38)) -> 3 | B38: auth_totp_portal | C38: 0 | D38: 10 | E38: 10
A39: =IF(C39="",SUMPRODUCT($C$1:$D$1,$C39:$D39),SUMPRODUCT($C$2:$D$2,$C39:$D39)) -> 0 | B39: barcodes | C39: 0 | D39: 0 | E39: 0
A40: =IF(C40="",SUMPRODUCT($C$1:$D$1,$C40:$D40),SUMPRODUCT($C$2:$D$2,$C40:$D40)) -> 0 | B40: barcodes_gs1_nomenclature | C40: 0 | D40: 0 | E40: 0
A41: =IF(C41="",SUMPRODUCT($C$1:$D$1,$C41:$D41),SUMPRODUCT($C$2:$D$2,$C41:$D41)) -> 0 | B41: base | D41: 0 | E41: 0
A42: =IF(C42="",SUMPRODUCT($C$1:$D$1,$C42:$D42),SUMPRODUCT($C$2:$D$2,$C42:$D42)) -> 0 | B42: base_address_extended | C42: 0 | D42: 0 | E42: 0
A43: =IF(C43="",SUMPRODUCT($C$1:$D$1,$C43:$D43),SUMPRODUCT($C$2:$D$2,$C43:$D43)) -> 288 | B43: base_automation | C43: 95 | D43: 10 | E43: 105
A44: =IF(C44="",SUMPRODUCT($C$1:$D$1,$C44:$D44),SUMPRODUCT($C$2:$D$2,$C44:$D44)) -> 0 | B44: base_geolocalize | C44: 0 | D44: 0 | E44: 0
A45: =IF(C45="",SUMPRODUCT($C$1:$D$1,$C45:$D45),SUMPRODUCT($C$2:$D$2,$C45:$D45)) -> 3 | B45: base_iban | C45: 0 | D45: 10 | E45: 10
A46: =IF(C46="",SUMPRODUCT($C$1:$D$1,$C46:$D46),SUMPRODUCT($C$2:$D$2,$C46:$D46)) -> 0 | B46: base_import | C46: 0 | D46: 0 | E46: 0
A47: =IF(C47="",SUMPRODUCT($C$1:$D$1,$C47:$D47),SUMPRODUCT($C$2:$D$2,$C47:$D47)) -> 0 | B47: base_import_module | C47: 0 | D47: 0 | E47: 0
A48: =IF(C48="",SUMPRODUCT($C$1:$D$1,$C48:$D48),SUMPRODUCT($C$2:$D$2,$C48:$D48)) -> 3 | B48: base_install_request | C48: 0 | D48: 10 | E48: 10
A49: =IF(C49="",SUMPRODUCT($C$1:$D$1,$C49:$D49),SUMPRODUCT($C$2:$D$2,$C49:$D49)) -> 0 | B49: base_setup | C49: 0 | D49: 0 | E49: 0
A50: =IF(C50="",SUMPRODUCT($C$1:$D$1,$C50:$D50),SUMPRODUCT($C$2:$D$2,$C50:$D50)) -> 0 | B50: base_sparse_field | C50: 0 | D50: 0 | E50: 0
A51: =IF(C51="",SUMPRODUCT($C$1:$D$1,$C51:$D51),SUMPRODUCT($C$2:$D$2,$C51:$D51)) -> 0 | B51: base_vat | C51: 0 | D51: 0 | E51: 0
A52: =IF(C52="",SUMPRODUCT($C$1:$D$1,$C52:$D52),SUMPRODUCT($C$2:$D$2,$C52:$D52)) -> 0 | B52: board | C52: 0 | D52: 0 | E52: 0
A53: =IF(C53="",SUMPRODUCT($C$1:$D$1,$C53:$D53),SUMPRODUCT($C$2:$D$2,$C53:$D53)) -> 0 | B53: bus | C53: 0 | D53: 0 | E53: 0
... A89: =IF(C89="",SUMPRODUCT($C$1:$D$1,$C89:$D89),SUMPRODUCT($C$2:$D$2,$C89:$D89)) -> 0 | B89: hr_holidays_attendance | C89: 0 | D89: 0 | E89: 0
A90: =IF(C90="",SUMPRODUCT($C$1:$D$1,$C90:$D90),SUMPRODUCT($C$2:$D$2,$C90:$D90)) -> 78 | B90: hr_homeworking | D90: 26 | E90: 26
A91: =IF(C91="",SUMPRODUCT($C$1:$D$1,$C91:$D91),SUMPRODUCT($C$2:$D$2,$C91:$D91)) -> 0 | B91: hr_hourly_cost | C91: 0 | D91: 0 | E91: 0
A92: =IF(C92="",SUMPRODUCT($C$1:$D$1,$C92:$D92),SUMPRODUCT($C$2:$D$2,$C92:$D92)) -> 30 | B92: hr_livechat | D92: 10 | E92: 10
A93: =IF(C93="",SUMPRODUCT($C$1:$D$1,$C93:$D93),SUMPRODUCT($C$2:$D$2,$C93:$D93)) -> 3 | B93: hr_maintenance | C93: 0 | D93: 10 | E93: 10
A94: =IF(C94="",SUMPRODUCT($C$1:$D$1,$C94:$D94),SUMPRODUCT($C$2:$D$2,$C94:$D94)) -> 3.3 | B94: hr_org_chart | C94: 0 | D94: 11 | E94: 11
A95: =IF(C95="",SUMPRODUCT($C$1:$D$1,$C95:$D95),SUMPRODUCT($C$2:$D$2,$C95:$D95)) -> 6.3 | B95: hr_presence | C95: 0 | D95: 21 | E95: 21
A96: =IF(C96="",SUMPRODUCT($C$1:$D$1,$C96:$D96),SUMPRODUCT($C$2:$D$2,$C96:$D96)) -> 130.2 | B96: hr_recruitment | C96: 0 | D96: 434 | E96: 434
A97: =IF(C97="",SUMPRODUCT($C$1:$D$1,$C97:$D97),SUMPRODUCT($C$2:$D$2,$C97:$D97)) -> 54.3 | B97: hr_recruitment_skills | C97: 10 | D97: 81 | E97: 91
A98: =IF(C98="",SUMPRODUCT($C$1:$D$1,$C98:$D98),SUMPRODUCT($C$2:$D$2,$C98:$D98)) -> 6.9 | B98: hr_recruitment_survey | C98: 0 | D98: 23 | E98: 23
A99: =IF(C99="",SUMPRODUCT($C$1:$D$1,$C99:$D99),SUMPRODUCT($C$2:$D$2,$C99:$D99)) -> 102.3 | B99: hr_skills | C99: 31 | D99: 31 | E99: 62
A100: =IF(C100="",SUMPRODUCT($C$1:$D$1,$C100:$D100),SUMPRODUCT($C$2:$D$2,$C100:$D100)) -> 0 | B100: hr_skills_slides | C100: 0 | D100: 0 | E100: 0
A101: =IF(C101="",SUMPRODUCT($C$1:$D$1,$C101:$D101),SUMPRODUCT($C$2:$D$2,$C101:$D101)) -> 64.5 | B101: hr_skills_survey | C101: 20 | D101: 15 | E101: 35
A102: =IF(C102="",SUMPRODUCT($C$1:$D$1,$C102:$D102),SUMPRODUCT($C$2:$D$2,$C102:$D102)) -> 8.1 | B102: hr_timesheet | C102: 0 | D102: 27 | E102: 27
A103: =IF(C103="",SUMPRODUCT($C$1:$D$1,$C103:$D103),SUMPRODUCT($C$2:$D$2,$C103:$D103)) -> 0 | B103: hr_timesheet_attendance | C103: 0 | D103: 0 | E103: 0
A104: =IF(C104="",SUMPRODUCT($C$1:$D$1,$C104:$D104),SUMPRODUCT($C$2:$D$2,$C104:$D104)) -> 49.5 | B104: hr_work_entry | C104: 15 | D104: 15 | E104: 30
... A117: =IF(C117="",SUMPRODUCT($C$1:$D$1,$C117:$D117),SUMPRODUCT($C$2:$D$2,$C117:$D117)) -> 98.1 | B117: l10n_ae | C117: 30 | D117: 27 | E117: 57
A118: =IF(C118="",SUMPRODUCT($C$1:$D$1,$C118:$D118),SUMPRODUCT($C$2:$D$2,$C118:$D118)) -> 180 | B118: l10n_ae_pos | C118: 60 | E118: 60
A119: =IF(C119="",SUMPRODUCT($C$1:$D$1,$C119:$D119),SUMPRODUCT($C$2:$D$2,$C119:$D119)) -> 60 | B119: l10n_anz_ubl_pint | D119: 20 | E119: 20
A120: =IF(C120="",SUMPRODUCT($C$1:$D$1,$C120:$D120),SUMPRODUCT($C$2:$D$2,$C120:$D120)) -> 216 | B120: l10n_ar | C120: 70 | D120: 20 | E120: 90
A121: =IF(C121="",SUMPRODUCT($C$1:$D$1,$C121:$D121),SUMPRODUCT($C$2:$D$2,$C121:$D121)) -> 30 | B121: l10n_ar_pos | D121: 10 | E121: 10
A122: =IF(C122="",SUMPRODUCT($C$1:$D$1,$C122:$D122),SUMPRODUCT($C$2:$D$2,$C122:$D122)) -> 33 | B122: l10n_ar_website_sale | C122: 10 | D122: 10 | E122: 20
A123: =IF(C123="",SUMPRODUCT($C$1:$D$1,$C123:$D123),SUMPRODUCT($C$2:$D$2,$C123:$D123)) -> 444 | B123: l10n_ar_withholding | D123: 148 | E123: 148
A124: =IF(C124="",SUMPRODUCT($C$1:$D$1,$C124:$D124),SUMPRODUCT($C$2:$D$2,$C124:$D124)) -> 402 | B124: l10n_at | C124: 133 | D124: 10 | E124: 143
A125: =IF(C125="",SUMPRODUCT($C$1:$D$1,$C125:$D125),SUMPRODUCT($C$2:$D$2,$C125:$D125)) -> 99.6 | B125: l10n_au | C125: 32 | D125: 12 | E125: 44
A126: =IF(C126="",SUMPRODUCT($C$1:$D$1,$C126:$D126),SUMPRODUCT($C$2:$D$2,$C126:$D126)) -> 30 | B126: l10n_bd | D126: 10 | E126: 10
A127: =IF(C127="",SUMPRODUCT($C$1:$D$1,$C127:$D127),SUMPRODUCT($C$2:$D$2,$C127:$D127)) -> 310.5 | B127: l10n_be | C127: 102 | D127: 15 | E127: 117
A128: =IF(C128="",SUMPRODUCT($C$1:$D$1,$C128:$D128),SUMPRODUCT($C$2:$D$2,$C128:$D128)) -> 33 | B128: l10n_be_pos_sale | C128: 10 | D128: 10 | E128: 20
A129: =IF(C129="",SUMPRODUCT($C$1:$D$1,$C129:$D129),SUMPRODUCT($C$2:$D$2,$C129:$D129)) -> 30 | B129: l10n_bf | D129: 10 | E129: 10
A130: =IF(C130="",SUMPRODUCT($C$1:$D$1,$C130:$D130),SUMPRODUCT($C$2:$D$2,$C130:$D130)) -> 168 | B130: l10n_bg | C130: 55 | D130: 10 | E130: 65
A131: =IF(C131="",SUMPRODUCT($C$1:$D$1,$C131:$D131),SUMPRODUCT($C$2:$D$2,$C131:$D131)) -> 30 | B131: l10n_bh | D131: 10 | E131: 10
A132: =IF(C132="",SUMPRODUCT($C$1:$D$1,$C132:$D132),SUMPRODUCT($C$2:$D$2,$C132:$D132)) -> 30 | B132: l10n_bj | D132: 10 | E132: 10
A133: =IF(C133="",SUMPRODUCT($C$1:$D$1,$C133:$D133),SUMPRODUCT($C$2:$D$2,$C133:$D133)) -> 96 | B133: l10n_bo | C133: 31 | D133: 10 | E133: 41
A134: =IF(C134="",SUMPRODUCT($C$1:$D$1,$C134:$D134),SUMPRODUCT($C$2:$D$2,$C134:$D134)) -> 823.5 | B134: l10n_br | C134: 159 | D134: 1155 | E134: 1314
A135: =IF(C135="",SUMPRODUCT($C$1:$D$1,$C135:$D135),SUMPRODUCT($C$2:$D$2,$C135:$D135)) -> 0 | B135: l10n_br_pix | D135: 0 | E135: 0
A136: =IF(C136="",SUMPRODUCT($C$1:$D$1,$C136:$D136),SUMPRODUCT($C$2:$D$2,$C136:$D136)) -> 30 | B136: l10n_br_sales | D136: 10 | E136: 10
A137: =IF(C137="",SUMPRODUCT($C$1:$D$1,$C137:$D137),SUMPRODUCT($C$2:$D$2,$C137:$D137)) -> 30 | B137: l10n_br_website_sale | D137: 10 | E137: 10
A138: =IF(C138="",SUMPRODUCT($C$1:$D$1,$C138:$D138),SUMPRODUCT($C$2:$D$2,$C138:$D138)) -> 165 | B138: l10n_ca | C138: 54 | D138: 10 | E138: 64
A139: =IF(C139="",SUMPRODUCT($C$1:$D$1,$C139:$D139),SUMPRODUCT($C$2:$D$2,$C139:$D139)) -> 30 | B139: l10n_cd | D139: 10 | E139: 10
A140: =IF(C140="",SUMPRODUCT($C$1:$D$1,$C140:$D140),SUMPRODUCT($C$2:$D$2,$C140:$D140)) -> 30 | B140: l10n_cf | D140: 10 | E140: 10
A141: =IF(C141="",SUMPRODUCT($C$1:$D$1,$C141:$D141),SUMPRODUCT($C$2:$D$2,$C141:$D141)) -> 30 | B141: l10n_cg | D141: 10 | E141: 10
A142: =IF(C142="",SUMPRODUCT($C$1:$D$1,$C142:$D142),SUMPRODUCT($C$2:$D$2,$C142:$D142)) -> 201 | B142: l10n_ch | C142: 66 | D142: 10 | E142: 76
A143: =IF(C143="",SUMPRODUCT($C$1:$D$1,$C143:$D143),SUMPRODUCT($C$2:$D$2,$C143:$D143)) -> 33 | B143: l10n_ch_pos | C143: 10 | D143: 10 | E143: 20
A144: =IF(C144="",SUMPRODUCT($C$1:$D$1,$C144:$D144),SUMPRODUCT($C$2:$D$2,$C144:$D144)) -> 30 | B144: l10n_ci | D144: 10 | E144: 10
A145: =IF(C145="",SUMPRODUCT($C$1:$D$1,$C145:$D145),SUMPRODUCT($C$2:$D$2,$C145:$D145)) -> 135 | B145: l10n_cl | C145: 45 | D145: 0 | E145: 45
A146: =IF(C146="",SUMPRODUCT($C$1:$D$1,$C146:$D146),SUMPRODUCT($C$2:$D$2,$C146:$D146)) -> 30 | B146: l10n_cm | D146: 10 | E146: 10
A147: =IF(C147="",SUMPRODUCT($C$1:$D$1,$C147:$D147),SUMPRODUCT($C$2:$D$2,$C147:$D147)) -> 57 | B147: l10n_cn | C147: 19 | D147: 0 | E147: 19
A148: =IF(C148="",SUMPRODUCT($C$1:$D$1,$C148:$D148),SUMPRODUCT($C$2:$D$2,$C148:$D148)) -> 33 | B148: l10n_cn_city | C148: 10 | D148: 10 | E148: 20
...

Sheet Analysis
A1: Mig | B1: Minutes | C1: App | D1: Hours
A2: 16-17 | B2: =D2*24*60 -> 0 | C2: account | E2: None | F2: Done
A3: 16-17 | B3: =D3*24*60 -> 0 | F3: (Model: 11, Field: 269, XML: 134)
A4: 16-17 | B4: =D4*24*60 -> 0 | C4: account_check_printing | E4: None | F4: Nothing to do No DB layout changes.
A5: 16-17 | B5: =D5*24*60 -> 10 | C5: account_debit_note | D5: 0.0069444444 | E5: None | F5: To analyse(0:10)
A6: 16-17 | B6: =D6*24*60 -> 0 | F6: (XML: 1)
A7: 16-17 | B7: =D7*24*60 -> 0 | C7: account_edi | E7: None | F7: Done
A8: 16-17 | B8: =D8*24*60 -> 0 | F8: (XML: 2)
A9: 16-17 | B9: =D9*24*60 -> 25 | C9: account_edi_proxy_client | D9: 0.017361111 | E9: None | F9: To analyse(0:25)
A10: 16-17 | B10: =D10*24*60 -> 0 | F10: (Field: 3, XML: 3)
A11: 16-17 | B11: =D11*24*60 -> 0 | C11: account_edi_ubl_cii | E11: None | F11: Done
A12: 16-17 | B12: =D12*24*60 -> 0 | F12: (Field: 5, XML: 32)
A13: 16-17 | B13: =D13*24*60 -> 0 | C13: account_edi_ubl_cii_tax_extension | E13: None | F13: No DB layout changes.
A14: 16-17 | B14: =D14*24*60 -> 0 | C14: account_fleet | E14: None | F14: No DB layout changes.
A15: 16-17 | B15: =D15*24*60 -> 10 | C15: account_lock | D15: 0.0069444444 | E15: None | F15: To analyse(0:10)
A16: 16-17 | B16: =D16*24*60 -> 0 | C16: account_payment | E16: None | F16: Done
A17: 16-17 | B17: =D17*24*60 -> 0 | F17: (XML: 13)
A18: 16-17 | B18: =D18*24*60 -> 0 | C18: account_payment_invoice_online_payment_patch | E18: None | F18: Merged into account_payment
A19: 16-17 | B19: =D19*24*60 -> 0 | C19: account_qr_code_sepa | E19: None | F19: Nothing to do
A20: 16-17 | B20: =D20*24*60 -> 0 | C20: account_sequence | E20: None | F20: Merged into account
A21: 16-17 | B21: =D21*24*60 -> 25 | C21: account_tax_python | D21: 0.017361111 | E21: None | F21: To analyse(0:25)
A22: 16-17 | B22: =D22*24*60 -> 0 | F22: (Field: 3)
A23: 16-17 | B23: =D23*24*60 -> 10 | C23: account_test | D23: 0.0069444444 | E23: None | F23: To analyse(0:10)
A24: 16-17 | B24: =D24*24*60 -> 0 | C24: account_update_tax_tags | E24: None | F24: No DB layout changes.
A25: 16-17 | B25: =D25*24*60 -> 0 | C25: analytic | E25: None | F25: Done
A26: 16-17 | B26: =D26*24*60 -> 0 | F26: (Field: 9, XML: 3)
A27: 16-17 | B27: =D27*24*60 -> 0 | C27: association | E27: None | F27: Merged into membership
A28: 16-17 | B28: =D28*24*60 -> 0 | C28: attachment_indexation | E28: None | F28: Nothing to do
A29: 16-17 | B29: =D29*24*60 -> 0 | C29: auth_ldap | E29: None | F29: No DB layout changes.
A30: 16-17 | B30: =D30*24*60 -> 0 | C30: auth_oauth | E30: None | F30: Nothing to do No DB layout changes.
A31: 16-17 | B31: =D31*24*60 -> 0 | C31: auth_password_policy | E31: None | F31: Nothing to do
A32: 16-17 | B32: =D32*24*60 -> 10 | C32: auth_password_policy_portal | D32: 0.0069444444 | E32: None | F32: To analyse(0:10)
A33: 16-17 | B33: =D33*24*60 -> 0 | C33: auth_password_policy_signup | E33: None | F33: Nothing to do
A34: 16-17 | B34: =D34*24*60 -> 0 | C34: auth_signup | E34: None | F34: Done
A35: 16-17 | B35: =D35*24*60 -> 0 | F35: (XML: 3)
A36: 16-17 | B36: =D36*24*60 -> 0 | C36: auth_totp | E36: None | F36: Nothing to do No DB layout changes.
A37: 16-17 | B37: =D37*24*60 -> 0 | C37: auth_totp_mail | E37: None | F37: Nothing to do
A38: 16-17 | B38: =D38*24*60 -> 0 | F38: (XML: 1)
A39: 16-17 | B39: =D39*24*60 -> 0 | C39: auth_totp_mail_enforce | E39: None | F39: No DB layout changes.
A40: 16-17 | B40: =D40*24*60 -> 0 | C40: auth_totp_portal | E40: None | F40: Nothing to do
A41: 16-17 | B41: =D41*24*60 -> 0 | C41: barcodes | E41: None | F41: Nothing to do No DB layout changes.
A42: 16-17 | B42: =D42*24*60 -> 0 | C42: barcodes_gs1_nomenclature | E42: None | F42: Nothing to do No DB layout changes.
A43: 16-17 | B43: =D43*24*60 -> 0 | C43: base_address_extended | E43: None | F43: Nothing to do
A44: 16-17 | B44: =D44*24*60 -> 0 | F44: (XML: 1)
A45: 16-17 | B45: =D45*24*60 -> 95 | C45: base_automation | D45: 0.065972222 | E45: None | F45: To analyse(1:35)
A46: 16-17 | B46: =D46*24*60 -> 0 | F46: (Field: 17, XML: 2)
A47: 16-17 | B47: =D47*24*60 -> 0 | C47: base_geolocalize | E47: None | F47: Nothing to do
A48: 16-17 | B48: =D48*24*60 -> 0 | F48: (XML: 1)
A49: 16-17 | B49: =D49*24*60 -> 0 | C49: base_iban | E49: None | F49: Nothing to do
A50: 16-17 | B50: =D50*24*60 -> 0 | C50: base_import | E50: None | F50: Nothing to do
A51: 16-17 | B51: =D51*24*60 -> 0 | F51: (Model: 15, Field: 26, XML: 15)
A52: 16-17 | B52: =D52*24*60 -> 0 | C52: base_import_module | E52: None | F52: Nothing to do
A53: 16-17 | B53: =D53*24*60 -> 0 | F53: (Field: 1, XML: 4)
A54: 16-17 | B54: =D54*24*60 -> 0 | C54: base_install_request | E54: None | F54: Nothing to do No DB layout changes.
A55: 16-17 | B55: =D55*24*60 -> 0 | C55: base_setup | E55: None | F55: Nothing to do
A56: 16-17 | B56: =D56*24*60 -> 0 | C56: base_sparse_field | E56: None | F56: Nothing to do No DB layout changes.
A57: 16-17 | B57: =D57*24*60 -> 0 | C57: base_vat | E57: None | F57: Done
A58: 16-17 | B58: =D58*24*60 -> 0 | F58: (Field: 2)
A59: 16-17 | B59: =D59*24*60 -> 0 | C59: board | E59: None | F59: Nothing to do No DB layout changes.
A60: 16-17 | B60: =D60*24*60 -> 0 | C60: bus | E60: None | F60: Nothing to do No DB layout changes.
A61: 16-17 | B61: =D61*24*60 -> 0 | C61: calendar | E61: None | F61: Done
A62: 16-17 | B62: =D62*24*60 -> 0 | F62: (Model: 1, Field: 4, XML: 11)
A63: 16-17 | B63: =D63*24*60 -> 0 | C63: calendar_sms | E63: None | F63: Nothing to do
A64: 16-17 | B64: =D64*24*60 -> 0 | F64: (Field: 1)
A65: 16-17 | B65: =D65*24*60 -> 0 | C65: contacts | E65: None | F65: Nothing to do
A66: 16-17 | B66: =D66*24*60 -> 0 | C66: crm | E66: None | F66: Done
A67: 16-17 | B67: =D67*24*60 -> 0 | F67: (Field: 8, XML: 10)
A68: 16-17 | B68: =D68*24*60 -> 0 | C68: crm_iap_enrich | E68: None | F68: No DB layout changes.
A69: 16-17 | B69: =D69*24*60 -> 10 | C69: crm_iap_mine | D69: 0.0069444444 | E69: None | F69: To analyse(0:10)
A70: 16-17 | B70: =D70*24*60 -> 0 | F70: (XML: 2)
A71: 16-17 | B71: =D71*24*60 -> 0 | C71: crm_livechat | E71: None | F71: No DB layout changes.
A72: 16-17 | B72: =D72*24*60 -> 10 | C72: crm_mail_plugin | D72: 0.0069444444 | E72: None | F72: To analyse(0:10)
A73: 16-17 | B73: =D73*24*60 -> 0 | C73: crm_sms | E73: None | F73: Nothing to do
A74: 16-17 | B74: =D74*24*60 -> 0 | F74: (XML: 1)
A75: 16-17 | B75: =D75*24*60 -> 0 | C75: data_recycle | E75: None | F75: No DB layout changes.
A76: 16-17 | B76: =D76*24*60 -> 0 | C76: delivery | E76: None | F76: Done
A77: 16-17 | B77: =D77*24*60 -> 0 | F77: (Model: 1, Field: 33, XML: 35)
A78: 16-17 | B78: =D78*24*60 -> 0 | C78: delivery_mondialrelay | E78: None | F78: No DB layout changes.
A79: 16-17 | B79: =D79*24*60 -> 0 | C79: delivery_stock_picking_batch | E79: None | F79: No DB layout changes.
A80: 16-17 | B80: =D80*24*60 -> 0 | C80: digest | E80: None | F80: Done
A81: 16-17 | B81: =D81*24*60 -> 0 | F81: (XML: 5)
A82: 16-17 | B82: =D82*24*60 -> 0 | C82: event | E82: None | F82: Done
A83: 16-17 | B83: =D83*24*60 -> 0 | F83: (Field: 24, XML: 26)
A84: 16-17 | B84: =D84*24*60 -> 35 | C84: event_booth | D84: 0.024305556 | E84: None | F84: To analyse(0:35)
A85: 16-17 | B85: =D85*24*60 -> 0 | F85: (Field: 5)
A86: 16-17 | B86: =D86*24*60 -> 25 | C86: event_booth_sale | D86: 0.017361111 | E86: None | F86: To analyse(0:25)
A87: 16-17 | B87: =D87*24*60 -> 0 | F87: (Field: 3)
A88: 16-17 | B88: =D88*24*60 -> 0 | C88: event_crm | E88: None | F88: Nothing to do No DB layout changes.
A89: 16-17 | B89: =D89*24*60 -> 10 | C89: event_crm_sale | D89: 0.0069444444 | E89: None | F89: To analyse(0:10)
A90: 16-17 | B90: =D90*24*60 -> 0 | C90: event_sale | E90: None | F90: Done
A91: 16-17 | B91: =D91*24*60 -> 0 | F91: (Field: 7, XML: 2)
A92: 16-17 | B92: =D92*24*60 -> 0 | C92: event_sms | E92: None | F92: No DB layout changes.
A93: 16-17 | B93: =D93*24*60 -> 0 | C93: fleet | E93: None | F93: Nothing to do
A94: 16-17 | B94: =D94*24*60 -> 0 | F94: (Field: 23, XML: 3)
A95: 16-17 | B95: =D95*24*60 -> 0 | C95: gamification | E95: None | F95: Done
A96: 16-17 | B96: =D96*24*60 -> 0 | F96: (Field: 9, XML: 8)
A97: 16-17 | B97: =D97*24*60 -> 0 | C97: gamification_sale_crm | E97: None | F97: Nothing to do
A98: 16-17 | B98: =D98*24*60 -> 0 | C98: google_account | E98: None | F98: Nothing to do No DB layout changes.
A99: 16-17 | B99: =D99*24*60 -> 0 | C99: google_calendar | E99: None | F99: Nothing to do
A100: 16-17 | B100: =D100*24*60 -> 0 | F100: (Field: 2)
...

Sheet Cloc
F1: python odoo-bin cloc -c ../odoo.conf -d o18-mini2
F2: Python
F3: import re
F5: def add_line_breaks(text):
F6: """
F7: Add a line break between numbers and letters in the given text.
F8: """
F9: return re.sub(r'(\d)([a-zA-Z])', r'\1\n\2', text)
F11: def convert_to_csv(output_text):
F12: """
F13: Convert each line of the output text to CSV format.
F14: """
... F27: print(csv_output)
C29: 50 | D29: 50 | E29: 3 | F29: Data - Text to Columns
C31: Minutes | D31: Minutes | E31: EUR | F31: Odoo cloc | G31: Line | H31: Other | I31: Code
C32: =IFERROR(IF(VLOOKUP(F32,'Pivot Analysis'!B:B,1,0)=F32,"",""),G32/$C$29) | D32: =G32/$D$29 -> 996.12 | E32: =D32*$E$29 -> 2988.36 | F32: account | G32: 49806 | H32: 13020 | I32: 36786
C33: =IFERROR(IF(VLOOKUP(F33,'Pivot Analysis'!B:B,1,0)=F33,"",""),G33/$C$29) | D33: =G33/$D$29 -> 94.7 | E33: =D33*$E$29 -> 284.1 | F33: account_edi_ubl_cii | G33: 4735 | H33: 1302 | I33: 3433
C34: =IFERROR(IF(VLOOKUP(F34,'Pivot Analysis'!B:B,1,0)=F34,"",""),G34/$C$29) | D34: =G34/$D$29 -> 5.76 | E34: =D34*$E$29 -> 17.28 | F34: account_fleet | G34: 288 | H34: 56 | I34: 232
C35: =IFERROR(IF(VLOOKUP(F35,'Pivot Analysis'!B:B,1,0)=F35,"",""),G35/$C$29) | D35: =G35/$D$29 -> 46.98 | E35: =D35*$E$29 -> 140.94 | F35: account_payment | G35: 2349 | H35: 585 | I35: 1764
C36: =IFERROR(IF(VLOOKUP(F36,'Pivot Analysis'!B:B,1,0)=F36,"",""),G36/$C$29) | D36: =G36/$D$29 -> 50 | E36: =D36*$E$29 -> 150 | F36: analytic | G36: 2500 | H36: 464 | I36: 2036
C37: =IFERROR(IF(VLOOKUP(F37,'Pivot Analysis'!B:B,1,0)=F37,"",""),G37/$C$29) | D37: =G37/$D$29 -> 3.1 | E37: =D37*$E$29 -> 9.3 | F37: attachment_indexation | G37: 155 | H37: 31 | I37: 124
C38: =IFERROR(IF(VLOOKUP(F38,'Pivot Analysis'!B:B,1,0)=F38,"",""),G38/$C$29) | D38: =G38/$D$29 -> 29.1 | E38: =D38*$E$29 -> 87.3 | F38: auth_signup | G38: 1455 | H38: 285 | I38: 1170
C39: =IFERROR(IF(VLOOKUP(F39,'Pivot Analysis'!B:B,1,0)=F39,"",""),G39/$C$29) | D39: =G39/$D$29 -> 14.62 | E39: =D39*$E$29 -> 43.86 | F39: auth_totp | G39: 731 | H39: 152 | I39: 579
C40: =IFERROR(IF(VLOOKUP(F40,'Pivot Analysis'!B:B,1,0)=F40,"",""),G40/$C$29) | D40: =G40/$D$29 -> 5.02 | E40: =D40*$E$29 -> 15.06 | F40: auth_totp_mail | G40: 251 | H40: 58 | I40: 193
C41: =IFERROR(IF(VLOOKUP(F41,'Pivot Analysis'!B:B,1,0)=F41,"",""),G41/$C$29) | D41: =G41/$D$29 -> 8.08 | E41: =D41*$E$29 -> 24.24 | F41: auth_totp_portal | G41: 404 | H41: 76 | I41: 328
C42: =IFERROR(IF(VLOOKUP(F42,'Pivot Analysis'!B:B,1,0)=F42,"",""),G42/$C$29) | D42: =G42/$D$29 -> 22.9 | E42: =D42*$E$29 -> 68.7 | F42: barcodes | G42: 1145 | H42: 273 | I42: 872
C43: =IFERROR(IF(VLOOKUP(F43,'Pivot Analysis'!B:B,1,0)=F43,"",""),G43/$C$29) | D43: =G43/$D$29 -> 22.46 | E43: =D43*$E$29 -> 67.38 | F43: barcodes_gs1_nomenclature | G43: 1123 | H43: 193 | I43: 930
... C230: =IFERROR(IF(VLOOKUP(F230,'Pivot Analysis'!B:B,1,0)=F230,"",""),G230/$C$29) | D230: =G230/$D$29 -> 1.96 | E230: =D230*$E$29 -> 5.88 | F230: website_sms | G230: 98 | H230: 21 | I230: 77
